{"jrtibster": [{"screen_name": "TalktoBPI", "full_name": "BPI"}, {"screen_name": "govph", "full_name": "Official Gazette PH"}, {"screen_name": "mellow947", "full_name": "Mellow 94.7"}, {"screen_name": "BPItrade", "full_name": "BPI Trade"}, {"screen_name": "Doc4Dead", "full_name": "Raquel Fortun"}, {"screen_name": "TaoEssentials", "full_name": "Tao Essentials"}, {"screen_name": "senyores", "full_name": "~\u0b9c\u06e9\u06de\u06e9\u0b9c~Senyor~\u0b9c\u06e9\u06de\u06e9\u0b9c~"}, {"screen_name": "Tony88981", "full_name": "TradersApprentice"}, {"screen_name": "ANC_OnTheMoney", "full_name": "ANC On the Money"}, {"screen_name": "wddeguzman", "full_name": "Warren de Guzman"}, {"screen_name": "PhStockExchange", "full_name": "Phil. Stock Exchange"}, {"screen_name": "MMDA", "full_name": "Official MMDA"}, {"screen_name": "dost_pagasa", "full_name": "PAGASA-DOST"}, {"screen_name": "deanjorgebocobo", "full_name": "Dean Bocobo"}, {"screen_name": "itsWillyFerrell", "full_name": "Not Will Ferrell"}, {"screen_name": "ClarenceHouse", "full_name": "Clarence House"}, {"screen_name": "DalaiLama", "full_name": "Dalai Lama"}, {"screen_name": "momblogger", "full_name": "Noemi L. Dado"}, {"screen_name": "leahnavarro", "full_name": "Leah Navarro"}, {"screen_name": "9GAG", "full_name": "9GAG"}, {"screen_name": "teddyboylocsin", "full_name": "Teddy Locsin Jr."}, {"screen_name": "FakeNoynoy", "full_name": "Noynoy Aquino III"}, {"screen_name": "VhongX44", "full_name": "Vhong Navarro"}, {"screen_name": "YourAnonNews", "full_name": "Anonymous"}, {"screen_name": "senmiriam", "full_name": "Miriam Santiago"}, {"screen_name": "PresidentNoy", "full_name": "P-Noy"}, {"screen_name": "iamkarendavila", "full_name": "Karen Davila"}, {"screen_name": "ANCALERTS", "full_name": "ABS-CBN News Channel"}, {"screen_name": "mlq3", "full_name": "Manuel L. Quezon III"}, {"screen_name": "annecurtissmith", "full_name": "Anne Curtis-Smith"}, {"screen_name": "noynoyaquino", "full_name": "Noynoy Aquino"}, {"screen_name": "MsLeaSalonga", "full_name": "Lea Salonga"}, {"screen_name": "gmanews", "full_name": "GMA News"}, {"screen_name": "carlosceldran", "full_name": "carlosceldran"}], "philippinebeat": [{"screen_name": "JaimeFbregas1", "full_name": "Jaime F\u00e1bregas"}, {"screen_name": "theastronautmj", "full_name": "Mark"}, {"screen_name": "GundoWeiler", "full_name": "Gundo Weiler"}, {"screen_name": "PLM_Manila", "full_name": "Pamantasan ng Lungsod ng Maynila"}, {"screen_name": "EntrepreneurPH", "full_name": "Entrepreneur PH"}, {"screen_name": "Malala", "full_name": "Malala"}, {"screen_name": "Poynter", "full_name": "Poynter"}, {"screen_name": "iwant", "full_name": "iWant"}, {"screen_name": "Askmewhats", "full_name": "Askmewhats"}, {"screen_name": "li_saga", "full_name": "Lisa Garcia"}, {"screen_name": "jamjacob", "full_name": "jam jacob"}, {"screen_name": "nxthompson", "full_name": "Nicholas Thompson"}, {"screen_name": "Yescppicache", "full_name": "Cherry Pie Picache"}, {"screen_name": "chrgovph", "full_name": "CHR Philippines"}, {"screen_name": "inamarfs", "full_name": "Ina M."}, {"screen_name": "netflix", "full_name": "Netflix US"}, {"screen_name": "MarieKondo", "full_name": "Marie Kondo"}, {"screen_name": "FintechPH", "full_name": "Fintech Philippines"}, {"screen_name": "couldrynick", "full_name": "NICK COULDRY"}, {"screen_name": "talaphilippines", "full_name": "Tala Philippines"}, {"screen_name": "philipb4", "full_name": "Philip Brookes"}, {"screen_name": "catrionaelisa", "full_name": "Catriona Gray"}, {"screen_name": "DanSantos8", "full_name": "Dan Santos"}, {"screen_name": "imichaelvicente", "full_name": "Michael Vicente"}, {"screen_name": "picpanational", "full_name": "PICPA NATIONAL"}, {"screen_name": "DaniloRuego", "full_name": "Danilo Ruego"}, {"screen_name": "icbacungan", "full_name": "Ian Irving Bacungan"}, {"screen_name": "pressfreedom", "full_name": "Committee to Protect Journalists"}, {"screen_name": "PRSPofficial", "full_name": "Public Relations Society of the Philippines"}, {"screen_name": "fbanalytics", "full_name": "Facebook Analytics"}, {"screen_name": "fbnewsroom", "full_name": "Facebook Newsroom"}, {"screen_name": "megamomph", "full_name": "Aileen Dualan MD"}, {"screen_name": "TokyoTokyoPHL", "full_name": "Tokyo Tokyo PH"}, {"screen_name": "ShaneWallCTO", "full_name": "Shane Wall"}, {"screen_name": "gideonlasco", "full_name": "Gideon Lasco"}, {"screen_name": "yogapedia_com", "full_name": "Yogapedia"}, {"screen_name": "samuelcnn", "full_name": "Samuel Burke"}, {"screen_name": "arvindergujral", "full_name": "Arvinder Gujral"}, {"screen_name": "badassboz", "full_name": "Bozoma Saint John"}, {"screen_name": "popesprayernet", "full_name": "Pope\u2019s Worldwide Prayer Network \u2013 Vatican"}, {"screen_name": "raypasky", "full_name": "Ray Victor T Pascual"}, {"screen_name": "weatherchannel", "full_name": "The Weather Channel"}, {"screen_name": "PAUlovesMOM", "full_name": "supramommie"}, {"screen_name": "aprilcenedoza", "full_name": "April Cenedoza"}, {"screen_name": "Forecast51", "full_name": "The Weather News Channel Asia"}, {"screen_name": "LalamovePH", "full_name": "Lalamove Philippines"}, {"screen_name": "Maxicare", "full_name": "Maxicare 09178327044"}, {"screen_name": "Civil", "full_name": "Civil"}, {"screen_name": "TrendPhilippine", "full_name": "Trending.ph \u00a0\ud83c\uddf5\ud83c\udded"}, {"screen_name": "sofiatomacruz", "full_name": "Sofia Tomacruz"}, {"screen_name": "aiyanaquino", "full_name": "Ianne Aquino"}, {"screen_name": "peterpomeranzev", "full_name": "peter pomerantsev"}, {"screen_name": "hecklerforever8", "full_name": "The Professional Heckler"}, {"screen_name": "ateneopress", "full_name": "Ateneo Press"}, {"screen_name": "beyonzyline", "full_name": "Vian Manuel"}, {"screen_name": "factchecknet", "full_name": "IFCN"}, {"screen_name": "jcpunongbayan", "full_name": "JC Punongbayan"}, {"screen_name": "BernaPuyat", "full_name": "Berna Romulo Puyat"}, {"screen_name": "_gmDylan", "full_name": "Dylan Abainza Isip \u00a0\u269c"}, {"screen_name": "viajeracebuana", "full_name": "Jeane Louise :)"}, {"screen_name": "DrugArchivePh", "full_name": "The Drug Archive Philippines"}, {"screen_name": "davidaklar", "full_name": "David A. Klar \u00a0\ud83c\udf41"}, {"screen_name": "ICIEInfoEthics", "full_name": "ICIE"}, {"screen_name": "karolyee", "full_name": "Karol Mark Yee"}, {"screen_name": "starbucksph", "full_name": "Starbucks Philippines"}, {"screen_name": "UNEnvironment", "full_name": "UN Environment"}, {"screen_name": "SpaceX", "full_name": "SpaceX"}, {"screen_name": "rustansfresh", "full_name": "Rustan's Supermarket"}, {"screen_name": "noelledeg", "full_name": "GUUUUUUUURL"}, {"screen_name": "RoyalFamily", "full_name": "The Royal Family"}, {"screen_name": "k8alvarez", "full_name": "Kate Alvarez"}, {"screen_name": "silver_black21", "full_name": "Chris"}, {"screen_name": "techtalks_ph", "full_name": "TechTalks.ph"}, {"screen_name": "mikeecj", "full_name": "Mikee C. Jaworski"}, {"screen_name": "DreLevinge", "full_name": "Dre"}, {"screen_name": "elonmusk", "full_name": "Elon Musk"}, {"screen_name": "gideonpena", "full_name": "Gideon Pe\u00f1a"}, {"screen_name": "erwanheussaff", "full_name": "Erwan Heussaff"}, {"screen_name": "Chekakramer", "full_name": "Chesca Garcia"}, {"screen_name": "MarcNelson_", "full_name": "Marc Nelson"}, {"screen_name": "ErikHuberman", "full_name": "Erik Huberman"}, {"screen_name": "richarboleda", "full_name": "Rich"}, {"screen_name": "RenzArgao", "full_name": "Renz Argao"}, {"screen_name": "guingonabart", "full_name": "Bart Guingona"}, {"screen_name": "karolilagan", "full_name": "Karol Ilagan"}, {"screen_name": "jonathan_c_ong", "full_name": "Jonathan Corpus Ong"}, {"screen_name": "econcepcion", "full_name": "Ethel"}, {"screen_name": "schiste", "full_name": "Christophe Henner"}, {"screen_name": "USTAAi", "full_name": "UST Alumni Assoc Inc."}, {"screen_name": "UST_CSC", "full_name": "UST CSC"}, {"screen_name": "MrSilverScott", "full_name": "Jonathan Silver Scott"}, {"screen_name": "MrDrewScott", "full_name": "Drew Scott"}, {"screen_name": "hgtv", "full_name": "HGTV"}, {"screen_name": "FixerUpperFans", "full_name": "Fixer Upper"}, {"screen_name": "joannagaines", "full_name": "Joanna Gaines"}, {"screen_name": "chipgaines", "full_name": "Chip Gaines"}, {"screen_name": "dataprivacyasia", "full_name": "Data Privacy Asia"}, {"screen_name": "thina_rsw", "full_name": "Thina"}, {"screen_name": "PinoyAkoBlog", "full_name": "PinoyAkoBlog"}, {"screen_name": "Imitation_mom", "full_name": "Imitationmom"}, {"screen_name": "KeithJKrach", "full_name": "Keith Krach"}, {"screen_name": "AdoboHamburger", "full_name": "AdoboHamburger"}, {"screen_name": "NawawalaPH", "full_name": "#NawawalaPH"}, {"screen_name": "tldtoday", "full_name": "Jonathan Morrison"}, {"screen_name": "MKBHD", "full_name": "Marques Brownlee"}, {"screen_name": "dbrand", "full_name": "dbrand"}, {"screen_name": "gethavenapp", "full_name": "Haven"}, {"screen_name": "JoannDArce", "full_name": "Joann Arce, PhD"}, {"screen_name": "lyndonleesuymd", "full_name": "Lyndon L. Lee Suy"}, {"screen_name": "ogie_rosa", "full_name": "Ogie Rosa"}, {"screen_name": "drsusanmercado", "full_name": "Susan Mercado"}, {"screen_name": "AntonioDans", "full_name": "Antonio Dans"}, {"screen_name": "byDianaMarks", "full_name": "Diana Marks"}, {"screen_name": "leloyclaudio", "full_name": "Leloy Claudio"}, {"screen_name": "Starshadow", "full_name": "cindyg aka Starshadow Rivaulx"}, {"screen_name": "julieposetti", "full_name": "Julie Posetti"}, {"screen_name": "MaksCzuperski", "full_name": "Maks Czuperski"}, {"screen_name": "GrahamBrookie", "full_name": "Graham Brookie"}, {"screen_name": "carlynyst", "full_name": "Carly Kind (Nyst)"}, {"screen_name": "IvanSaldajeno", "full_name": "Ivan Saldajeno"}, {"screen_name": "DHLexpress", "full_name": "DHL Express"}, {"screen_name": "RegisAndanar", "full_name": "Regis Andanar"}, {"screen_name": "WomenInfluence_", "full_name": "Women Influence Club"}, {"screen_name": "AceGapuz", "full_name": "Ace Gapuz"}, {"screen_name": "EU_AseanBC", "full_name": "EU-ASEAN Biz Council"}, {"screen_name": "letsgonegosyo", "full_name": "Go Negosyo Official"}, {"screen_name": "danotingcungco", "full_name": "Dano Tingcungco"}, {"screen_name": "mylaurin", "full_name": "Laurin CocoMCT"}, {"screen_name": "justinjoyas", "full_name": "Justin Joyas"}, {"screen_name": "NetizenFour", "full_name": "Jared Bielby"}, {"screen_name": "TheCoffeeBean", "full_name": "The Coffee Bean"}, {"screen_name": "ateneo_acfj", "full_name": "ACFJ at Ateneo"}, {"screen_name": "erikavose", "full_name": "mom sets the table"}, {"screen_name": "eCitizenHK", "full_name": "Digital Citizenship"}, {"screen_name": "BuhayMovement", "full_name": "Buhay Movement"}, {"screen_name": "TimSmalley", "full_name": "Tim Smalley"}, {"screen_name": "ADigitalCitizen", "full_name": "Digital Citizenship"}, {"screen_name": "wearesocial", "full_name": "We Are Social"}, {"screen_name": "JoelOsteen", "full_name": "Joel Osteen"}, {"screen_name": "johnsamuelyap", "full_name": "Sam Yap"}, {"screen_name": "assortedge", "full_name": "Assortedge"}, {"screen_name": "RadmallAndre", "full_name": "Andre Radmall"}, {"screen_name": "CarlReader", "full_name": "Carl Reader"}, {"screen_name": "AccentureJobsPH", "full_name": "AccenturePhilippines"}, {"screen_name": "WarcAsia", "full_name": "WARC Asia Pacific"}, {"screen_name": "edpank", "full_name": "Ed Pank"}, {"screen_name": "thejammagno", "full_name": "Jam Magno"}, {"screen_name": "mrsolis", "full_name": "MrSolis"}, {"screen_name": "SheelMajumdar", "full_name": "Sheel Majumdar"}, {"screen_name": "briansolis", "full_name": "Brian Solis"}, {"screen_name": "DENR_EnviBureau", "full_name": "DENR_EMBOfficial"}, {"screen_name": "HigalaFLC", "full_name": "Higala: Friends of the Lumad in Caraga"}, {"screen_name": "ThePUPOfficial", "full_name": "PUP (Official)"}, {"screen_name": "youngfutureph", "full_name": "YoungFuture"}, {"screen_name": "ucanphilippines", "full_name": "UCAN Philippines"}, {"screen_name": "maan_macapagal", "full_name": "Maan Macapagal"}, {"screen_name": "mariovdumaual", "full_name": "Mario Dumaual"}, {"screen_name": "joieccruz", "full_name": "Joie Cruz \u00a0\ud83c\uddf5\ud83c\udded"}, {"screen_name": "digitalfilipina", "full_name": "Digital Filipina"}, {"screen_name": "juicevill", "full_name": "Janice Villanueva"}, {"screen_name": "FrJett", "full_name": "Jose Ramon Villarin"}, {"screen_name": "fthilbay", "full_name": "Pilo Hilbay"}, {"screen_name": "AtheistDoctor", "full_name": "The Atheist Doctor"}, {"screen_name": "MarketWatch", "full_name": "MarketWatch"}, {"screen_name": "UmuulanPH", "full_name": "ULAN TRACKER PH"}, {"screen_name": "KensingtonRoyal", "full_name": "Kensington Palace"}, {"screen_name": "JayAgonoy", "full_name": "Jay Agonoy / keepsakes. @ #Otakufest2019"}, {"screen_name": "rambotalabong", "full_name": "Rambo Talabong"}, {"screen_name": "JerriAC", "full_name": "Alma Anonas-Carpio"}, {"screen_name": "ArcadeCityHall", "full_name": "Arcade City"}, {"screen_name": "WunderMobility", "full_name": "Wunder Mobility"}, {"screen_name": "APC_News", "full_name": "APC"}, {"screen_name": "laborgovph", "full_name": "DOLE Philippines"}, {"screen_name": "DolePhilippines", "full_name": "Dole PH"}, {"screen_name": "jpjbencito", "full_name": "John Paolo Bencito"}, {"screen_name": "ISAFEVentures", "full_name": "ISAFE Ventures"}, {"screen_name": "MathisenRoger", "full_name": "Roger Mathisen"}, {"screen_name": "juliewoodsmoss", "full_name": "Julie Woods-Moss"}, {"screen_name": "TutanotaTeam", "full_name": "Tutanota"}, {"screen_name": "gijn", "full_name": "GIJN"}, {"screen_name": "AwesomeAliceCom", "full_name": "Awesome Alice"}, {"screen_name": "Accenture", "full_name": "Accenture"}, {"screen_name": "kriscatadena", "full_name": "krisca tadena"}, {"screen_name": "byahebuddycom", "full_name": "Byahe Buddy"}, {"screen_name": "torproject", "full_name": "The Tor Project"}, {"screen_name": "DuckDuckGo", "full_name": "DuckDuckGo"}, {"screen_name": "letsencrypt", "full_name": "Let's Encrypt"}, {"screen_name": "emckirdy", "full_name": "Euan McKirdy"}, {"screen_name": "jan_lizardo", "full_name": "Janice LagmanLizardo"}, {"screen_name": "RealDonitaRose", "full_name": "Donita Rose"}, {"screen_name": "ipcigaral", "full_name": "Ian Nicolas Cigaral"}, {"screen_name": "carawelfarePH", "full_name": "CARA Welfare PH"}, {"screen_name": "CJMRagasa", "full_name": "Christian Ragasa"}, {"screen_name": "SMILECares_SCF", "full_name": "SMILECares Foundation"}, {"screen_name": "yespinoy", "full_name": "YesPinoy Foundation"}, {"screen_name": "iamdongdantes", "full_name": "Dingdong Dantes"}, {"screen_name": "upennlib", "full_name": "The Penn Libraries"}, {"screen_name": "PSAgovph", "full_name": "@PSAgovph"}, {"screen_name": "yabuPH", "full_name": "Yabu: House of Katsu"}, {"screen_name": "_HealthyOptions", "full_name": "Healthy Options PH"}, {"screen_name": "CreativesOfMNL", "full_name": "Creatives of Manila"}, {"screen_name": "TwitterVideo", "full_name": "Twitter Video"}, {"screen_name": "jgibbard", "full_name": "Jeff Gibbard"}, {"screen_name": "musicmuseumph", "full_name": "Music Museum Group"}, {"screen_name": "Teatrinoph", "full_name": "TeatrinoPh"}, {"screen_name": "ghcinemasph", "full_name": "ghcinemasph"}, {"screen_name": "MarcelHuetten", "full_name": "Marcel Huetten"}, {"screen_name": "arisytner", "full_name": "Ari Sytner, Ph.D."}, {"screen_name": "rcallimachi", "full_name": "Rukmini Callimachi"}, {"screen_name": "James__Craven", "full_name": "James Craven"}, {"screen_name": "SueScheff", "full_name": "Sue Scheff"}, {"screen_name": "LocnStor247", "full_name": "Loc&Stor 24/7 PH"}, {"screen_name": "KulasAndKumar", "full_name": "Becoming Filipino TV"}, {"screen_name": "literoflight", "full_name": "Liter of Light"}, {"screen_name": "KyleJennermann", "full_name": "Kyle Jennermann"}, {"screen_name": "wordpressdotcom", "full_name": "WordPress.com"}, {"screen_name": "TwitterWomen", "full_name": "Twitter Women"}, {"screen_name": "EmpowermentEss1", "full_name": "Empowerment Essence"}, {"screen_name": "ColinCrowell", "full_name": "Colin Crowell"}, {"screen_name": "TwitterForGood", "full_name": "Twitter for Good"}, {"screen_name": "Policy", "full_name": "Twitter Public Policy"}, {"screen_name": "kathleenreen", "full_name": "Kathleen Reen"}, {"screen_name": "TechWireAsia", "full_name": "Tech Wire Asia"}, {"screen_name": "XplodingUnicorn", "full_name": "James Breakwell, Exploding Unicorn"}, {"screen_name": "KaPaengMariano", "full_name": "Rafael V. Mariano"}, {"screen_name": "visacommunity", "full_name": "VisaCommunity"}, {"screen_name": "shakirasison", "full_name": "Shakira Sison"}, {"screen_name": "trendinaliaPI", "full_name": "Trendinalia Philippines \u00a0\ud83c\uddf5\ud83c\udded"}, {"screen_name": "ValaAfshar", "full_name": "Vala Afshar"}, {"screen_name": "CapgeminiInvent", "full_name": "Capgemini Invent"}, {"screen_name": "MichelleYarn", "full_name": "Michelle Yarn"}, {"screen_name": "wordfence", "full_name": "Wordfence"}, {"screen_name": "TitasOfCebu", "full_name": "TitasOfCebu"}, {"screen_name": "matthewtoren", "full_name": "Matthew Toren"}, {"screen_name": "iloveglorietta", "full_name": "Glorietta"}, {"screen_name": "GlobalChamMNL", "full_name": "Global Manila"}, {"screen_name": "BrianDEvans", "full_name": "Brian D. Evans"}, {"screen_name": "dondimapa", "full_name": "Dondi Mapa"}, {"screen_name": "iGovPhilProgram", "full_name": "iGovPhil Program"}, {"screen_name": "HollyKrambeck", "full_name": "Holly Krambeck"}, {"screen_name": "ceciletamura", "full_name": "Cecile Tamura"}, {"screen_name": "MLCActiveSports", "full_name": "Yoga by MLC"}, {"screen_name": "CSI_2019", "full_name": "Cyber Security INA"}, {"screen_name": "PlanetWaterCEO", "full_name": "Mark Steele \u00a0\ud83d\udca7"}, {"screen_name": "EllenAlarilla", "full_name": "Ellen Alarilla"}, {"screen_name": "ajagrawal24", "full_name": "AJ Agrawal"}, {"screen_name": "Bill_Luz", "full_name": "Guillermo Luz"}, {"screen_name": "CompetitionPH", "full_name": "PCC"}, {"screen_name": "NTCPH", "full_name": "NTC"}, {"screen_name": "NSmith", "full_name": "N\u1d00\u0274\u1d04\u028f S\u1d0d\u026a\u1d1b\u029c"}, {"screen_name": "AteneOBF", "full_name": "Team Ateneo"}, {"screen_name": "admuheartstrong", "full_name": "Ateneo Lady Eagles"}, {"screen_name": "okadamanila", "full_name": "Okada Manila"}, {"screen_name": "Hondaphil", "full_name": "Honda Cars Philippines"}, {"screen_name": "danielthrelfall", "full_name": "Daniel Threlfall"}, {"screen_name": "USEmbassyPHSpox", "full_name": "Molly Koscina"}, {"screen_name": "philihub", "full_name": "Philihub\u2122"}, {"screen_name": "JennyRockwell", "full_name": "JenniferTanRockwell"}, {"screen_name": "FrenchEmbassyPH", "full_name": "France in the PH \u00a0\ud83c\uddeb\ud83c\uddf7\u00a0\ud83c\uddf5\ud83c\udded"}, {"screen_name": "jennysanti", "full_name": "Jenny Santi"}, {"screen_name": "HealingMB", "full_name": "Mindfulness Wellness"}, {"screen_name": "KLM", "full_name": "Royal Dutch Airlines"}, {"screen_name": "DOST_projnoah", "full_name": "DOST-Project NOAH"}, {"screen_name": "Youth4MH", "full_name": "Youth for Mental Health Coalition, Inc."}, {"screen_name": "isamuel", "full_name": "Ian Samuel"}, {"screen_name": "rayanposadas", "full_name": "rayan"}, {"screen_name": "CTrappe", "full_name": "Christoph Trappe"}, {"screen_name": "bashfreephil", "full_name": "Bashfree PH"}, {"screen_name": "JamesVelinaLXIX", "full_name": "James Romer  Velina"}, {"screen_name": "choihiLario", "full_name": "Choi Hilario"}, {"screen_name": "SEFPinol", "full_name": "Emmanuel F. Pi\u00f1ol"}, {"screen_name": "DonTiburcio", "full_name": "Steven T. Cua"}, {"screen_name": "lizlanuzo", "full_name": "Liz Lanuzo"}, {"screen_name": "peggyapl", "full_name": "peggy aplSEEDS"}, {"screen_name": "cammipham", "full_name": "Cammi Pham| eCommerce Marketer"}, {"screen_name": "SaqibIslam", "full_name": "Saqib Ul Islam"}, {"screen_name": "pie_rivera", "full_name": "HEART'S CONTENT"}, {"screen_name": "POTUS", "full_name": "President Trump"}, {"screen_name": "1abuazzam", "full_name": "Nordin Pumbaya"}, {"screen_name": "junrobleslana", "full_name": "Jun Robles Lana"}, {"screen_name": "indiohistorian", "full_name": "Kristoffer Pasion"}, {"screen_name": "citizenjaneph", "full_name": "Citizen Jane (Uymatiao)"}, {"screen_name": "shecrisostomo", "full_name": "sheila crisostomo"}, {"screen_name": "ImoiraL", "full_name": "Moira Lang"}, {"screen_name": "AskAimeeBeck", "full_name": "Aimee Beck"}, {"screen_name": "paulfroberts", "full_name": "Paul Roberts"}, {"screen_name": "imsmartinc", "full_name": "imsmartin"}, {"screen_name": "sean_martin", "full_name": "Sean Martin, CISSP"}, {"screen_name": "ITSPmagazine", "full_name": "ITSPmagazine"}, {"screen_name": "imjennyortiz", "full_name": "Jenny Ortiz"}, {"screen_name": "minapalencia", "full_name": "Mina Palencia"}, {"screen_name": "InfosecurityMag", "full_name": "Infosecurity Mag"}, {"screen_name": "threatpost", "full_name": "Threatpost"}, {"screen_name": "dutchsinse", "full_name": "dutchsinse"}, {"screen_name": "titatechie", "full_name": "Tita Jane"}, {"screen_name": "1nutty_hazel", "full_name": "Hazel Nutella"}, {"screen_name": "geraldinebroman", "full_name": "Geraldine Roman"}, {"screen_name": "panasonicph", "full_name": "PanasonicPhilippines"}, {"screen_name": "mmffofficial", "full_name": "MMFF Official"}, {"screen_name": "UN_Women", "full_name": "UN Women"}, {"screen_name": "DgteTourism", "full_name": "Dumaguete Tourism"}, {"screen_name": "Lou4loos", "full_name": "Louise Maule"}, {"screen_name": "x0rz", "full_name": "x0rz"}, {"screen_name": "theTunnelBear", "full_name": "TunnelBear"}, {"screen_name": "AntipoloCityGov", "full_name": "Antipolo City Gov"}, {"screen_name": "ilovekikkoman", "full_name": "Francis J. Ricamora"}, {"screen_name": "WPUGPH", "full_name": "WP User Group PH"}, {"screen_name": "vocativ", "full_name": "Vocativ"}, {"screen_name": "BBCtrending", "full_name": "BBC Trending"}, {"screen_name": "PatMangune", "full_name": "Pat Mangune TV5"}, {"screen_name": "takebackthetech", "full_name": "Take Back the Tech!"}, {"screen_name": "c5", "full_name": "c5"}, {"screen_name": "SiriouslySusan", "full_name": "Susan Bennett"}, {"screen_name": "clarissadavid2", "full_name": "clarissa david"}, {"screen_name": "Pulitika2010", "full_name": "Stella Arnaldo"}, {"screen_name": "hwnddawg", "full_name": "Winthrop Yu"}, {"screen_name": "thecorpusjuris", "full_name": "The Corpus Juris \u00a0\u2696\ufe0f"}, {"screen_name": "MrFrankBaraan", "full_name": "Francis Baraan IV"}, {"screen_name": "AltMedBlogs", "full_name": "Alternative Medicine"}, {"screen_name": "thysz", "full_name": "Thysz #DefendPressFreedom"}, {"screen_name": "tjgarceau", "full_name": "ThereseJamoraGarceau"}, {"screen_name": "Rizal_Library", "full_name": "Rizal Library"}, {"screen_name": "NikiTaylorInc", "full_name": "Niki Taylor"}, {"screen_name": "TeamAMDG", "full_name": "Team AMDG"}, {"screen_name": "firstdraftnews", "full_name": "First Draft"}, {"screen_name": "waltmossberg", "full_name": "Walt Mossberg"}, {"screen_name": "Techmeme", "full_name": "Techmeme"}, {"screen_name": "realDonaldTrump", "full_name": "Donald J. Trump"}, {"screen_name": "bloombergtvph", "full_name": "BloombergTVPh"}, {"screen_name": "emilyrauhala", "full_name": "Emily Rauhala"}, {"screen_name": "davidlozadamds", "full_name": "David Bryan Lozada"}, {"screen_name": "SmartNewsroom", "full_name": "Smart Newsroom"}, {"screen_name": "KenRoth", "full_name": "Kenneth Roth"}, {"screen_name": "Senyora", "full_name": "SENYORA"}, {"screen_name": "David_Tapang", "full_name": "David Tapang"}, {"screen_name": "MichBayhonan", "full_name": "Michelle Bayhonan"}, {"screen_name": "richardbranson", "full_name": "Richard Branson"}, {"screen_name": "healthcubeph", "full_name": "Health Cube Clinics"}, {"screen_name": "melvsgc", "full_name": "Melvin Calimag"}, {"screen_name": "autoceremony", "full_name": "Jing Garcia"}, {"screen_name": "alexeivee", "full_name": "Alexei"}, {"screen_name": "huaweimobileph", "full_name": "Huawei Mobile PH"}, {"screen_name": "PiaWurtzbach", "full_name": "Pia Alonzo Wurtzbach"}, {"screen_name": "KylieVerzosa", "full_name": "Kylie"}, {"screen_name": "IntertrustTech", "full_name": "Intertrust Tech"}, {"screen_name": "ProtonMail", "full_name": "ProtonMail"}, {"screen_name": "AmyPerezOFC", "full_name": "Amy Perez OFFICIAL FansClub"}, {"screen_name": "MdeQuirosABSCBN", "full_name": "Miranda de Quiros"}, {"screen_name": "davidyusantos", "full_name": "David Y. Santos"}, {"screen_name": "cheriemercado", "full_name": "Cherie Mercado"}, {"screen_name": "JCGotinga", "full_name": "JC Gotinga"}, {"screen_name": "anjocalimario", "full_name": "Anjo Cagmat Alimario"}, {"screen_name": "gergcahiles", "full_name": "Gerg Cahiles"}, {"screen_name": "ruthcabal15", "full_name": "Ruth Cabal"}, {"screen_name": "cedric_castillo", "full_name": "Cedric Castillo"}, {"screen_name": "HotchkissWeb", "full_name": "Sam Hotchkiss"}, {"screen_name": "jetpack", "full_name": "Jetpack"}, {"screen_name": "AnnZuccardy", "full_name": "Ann Zuccardy"}, {"screen_name": "Manay_Judy", "full_name": "Manay Judy Taguiwalo"}, {"screen_name": "kaloi_zarate", "full_name": "RepCarlos.I.T.Zarate"}, {"screen_name": "UNYorikoY", "full_name": "Yoriko Yasukawa"}, {"screen_name": "KlausBeck_", "full_name": "Klaus Beck"}, {"screen_name": "UNFPAasia", "full_name": "UNFPA Asia & Pacific"}, {"screen_name": "iCyclone", "full_name": "Josh Morgerman"}, {"screen_name": "missElainenews", "full_name": "Elaine Alanguilan"}, {"screen_name": "oxygenixon", "full_name": "genixon david"}, {"screen_name": "guardiantech", "full_name": "Guardian Tech"}, {"screen_name": "futureshift", "full_name": "FutureShift"}, {"screen_name": "cnntech", "full_name": "CNN Tech"}, {"screen_name": "RCBCSavingsBank", "full_name": "RCBC Savings Bank"}, {"screen_name": "chinabankph", "full_name": "China Bank PH"}, {"screen_name": "OfficialSLEX", "full_name": "SLEX - MaTES"}, {"screen_name": "anthonywx", "full_name": "Anthony Sagliani"}, {"screen_name": "deejayapINQ", "full_name": "DJ Yap"}, {"screen_name": "inquirerplus", "full_name": "Inquirer Plus"}, {"screen_name": "bworldresearch", "full_name": "BWorld Research"}, {"screen_name": "beep_card", "full_name": "beep\u2122 card"}, {"screen_name": "ThomasReeseSJ", "full_name": "Thomas Reese, S.J."}, {"screen_name": "A21", "full_name": "A21"}, {"screen_name": "DotPh_Wonderful", "full_name": "Tourism Philippines"}, {"screen_name": "bbcaaron", "full_name": "Aaron Heslehurst"}, {"screen_name": "BBCLeisha", "full_name": "Leisha Chi Santorelli"}, {"screen_name": "According2Mandy", "full_name": "Mandy Robinson"}, {"screen_name": "ADHDPh", "full_name": "ADHD Society Phils"}, {"screen_name": "NGFoundationPH", "full_name": "NGFoundation"}, {"screen_name": "TimetoChange", "full_name": "Time to Change"}, {"screen_name": "mhtodaymag", "full_name": "Mental Health Today"}, {"screen_name": "mentalhealthph", "full_name": "MentalHealthPH"}, {"screen_name": "teknisyan", "full_name": "Abiel"}, {"screen_name": "CGTNOfficial", "full_name": "CGTN"}, {"screen_name": "kellymisa", "full_name": "Kelly Misa-Fernandez"}, {"screen_name": "BibopGGresta", "full_name": "Bibop G. Gresta"}, {"screen_name": "civildefensePH", "full_name": "Civil Defense PH"}, {"screen_name": "xianneangel", "full_name": "Xianne Arcangel"}, {"screen_name": "BEARBRAND_PMD", "full_name": "BEAR BRAND PMD"}, {"screen_name": "SecMelSarmiento", "full_name": "Mel Senen Sarmiento"}, {"screen_name": "HouseofRepsPH", "full_name": "The House PH"}, {"screen_name": "repfrancecastro", "full_name": "France L. Castro"}, {"screen_name": "speakeralvarez", "full_name": "Pantaleon D. Alvarez"}, {"screen_name": "MHPieperPhD", "full_name": "Martha H. Pieper PHD"}, {"screen_name": "teedubya", "full_name": "Travis Wright"}, {"screen_name": "miamgonzalez", "full_name": "Mia Gonzalez"}, {"screen_name": "UN", "full_name": "United Nations"}, {"screen_name": "Kickstartph", "full_name": "Kickstart"}, {"screen_name": "Coffeeph", "full_name": "Coffee Academy PH"}, {"screen_name": "Oxfam", "full_name": "Oxfam International"}, {"screen_name": "pacos1992", "full_name": "Paco Sandejas"}, {"screen_name": "CNET", "full_name": "CNET"}, {"screen_name": "womenintech", "full_name": "Women in Technology"}, {"screen_name": "yolycrisanto", "full_name": "Yoly C."}, {"screen_name": "Padme001", "full_name": "Minette Navarrete"}, {"screen_name": "OPPOPhilippines", "full_name": "OPPO Philippines"}, {"screen_name": "ronnasieh", "full_name": "Ronna Reyes Sieh"}, {"screen_name": "ThePDRF", "full_name": "PDRF"}, {"screen_name": "rupertambil", "full_name": "Rupert Ambil II"}, {"screen_name": "marco_lobregat", "full_name": "Marco Lobregat"}, {"screen_name": "MyPhoneOfficial", "full_name": "MyPhone"}, {"screen_name": "LeandroLeviste", "full_name": "Lean Legarda Leviste"}, {"screen_name": "SolarPhils", "full_name": "Solar Philippines"}, {"screen_name": "jayczster", "full_name": "Jake"}, {"screen_name": "JenniferGarrett", "full_name": "Jenny Garrett"}, {"screen_name": "briankrebs", "full_name": "briankrebs"}, {"screen_name": "janinegibson", "full_name": "Janine Gibson"}, {"screen_name": "TheJoeVizcarra", "full_name": "The Joe Vizcarra"}, {"screen_name": "thepinoybabbler", "full_name": "Billie MMC \u00a0\ud83c\udff3\ufe0f\u200d\ud83c\udf08"}, {"screen_name": "MollyKoscina", "full_name": "Molly Koscina"}, {"screen_name": "TheCooksCook", "full_name": "Denise Landis"}, {"screen_name": "mediaghosts", "full_name": "Michelle Ferrier"}, {"screen_name": "MurrayNewlands", "full_name": "Murray Newlands"}, {"screen_name": "shelleymiranda", "full_name": "Shelley Hepworth"}, {"screen_name": "yoursosteam", "full_name": "TrollBusters"}, {"screen_name": "travelbookph", "full_name": "Travelbook.ph"}, {"screen_name": "Payoneer", "full_name": "Payoneer"}, {"screen_name": "JervisManahan", "full_name": "Jervis Manahan"}, {"screen_name": "Rainwalker19", "full_name": "Dave Llorito"}, {"screen_name": "JoseMaNolasco", "full_name": "Joey Nolasco"}, {"screen_name": "colfinancial", "full_name": "COL Financial"}, {"screen_name": "geralynrigor", "full_name": "Geralyn Rigor"}, {"screen_name": "ernieabella", "full_name": "ERNIE ABELLA"}, {"screen_name": "adharves", "full_name": "Adam Harvey"}, {"screen_name": "huntandgatherph", "full_name": "Huntandgatherph"}, {"screen_name": "VPPilipinas", "full_name": "Vice President Leni"}, {"screen_name": "team48response", "full_name": "Team48 Response"}, {"screen_name": "jokowi", "full_name": "Joko Widodo"}, {"screen_name": "amkapunan", "full_name": "Anna Kapunan"}, {"screen_name": "GMA_BP", "full_name": "Balita Pilipinas"}, {"screen_name": "ashishjaiman", "full_name": "ashishjaiman"}, {"screen_name": "JonathanAndal_", "full_name": "Jonathan Andal"}, {"screen_name": "DILGPhilippines", "full_name": "DILG Philippines"}, {"screen_name": "DtiPhilippines", "full_name": "DTI Philippines"}, {"screen_name": "ahoyitseli", "full_name": "Elijah"}, {"screen_name": "Iyengarish", "full_name": "Rishi Iyengar"}, {"screen_name": "SMARTCares", "full_name": "SMARTCares"}, {"screen_name": "Ayalowe", "full_name": "Aya Lowe"}, {"screen_name": "camillediola", "full_name": "Camille Diola"}, {"screen_name": "PIA_4A", "full_name": "PIA CALABARZON"}, {"screen_name": "Kaspersky_PH", "full_name": "Kaspersky Lab PH"}, {"screen_name": "BROTHERPhils", "full_name": "Brother Philippines"}, {"screen_name": "PokemonLetsGoNS", "full_name": "Pokemon Let's GO! Pikachu & Eevee - INTEL"}, {"screen_name": "PokeWire", "full_name": "Pok\u00e9Wire"}, {"screen_name": "Adoptionism", "full_name": "Anthony"}, {"screen_name": "BlanchePGO", "full_name": "Blanche"}, {"screen_name": "Nelguh", "full_name": "Nelly \u00a0\ud83d\udd79"}, {"screen_name": "GoTeamMystic", "full_name": "TeamMystic PokemonGO"}, {"screen_name": "TeamMysticPGO", "full_name": "Team Mystic"}, {"screen_name": "_Mk_Ultra__", "full_name": "MK"}, {"screen_name": "GamerMag_", "full_name": "Gamer Magazine"}, {"screen_name": "PokeVisionGo", "full_name": "Pokevision"}, {"screen_name": "PokemonGoPhil", "full_name": "PokemonGoPhilippines"}, {"screen_name": "PayMayaOfficial", "full_name": "PayMaya"}, {"screen_name": "pulse_ph", "full_name": "Pulse Asia Research"}, {"screen_name": "TRBph", "full_name": "TollRegulatoryBoard"}, {"screen_name": "Marina2216", "full_name": "Marina Azcarate"}, {"screen_name": "flaircandy", "full_name": "flaircandy"}, {"screen_name": "CatchPokemonGo", "full_name": "PokemonGo"}, {"screen_name": "jisooyaaaaaah", "full_name": "bp is da revolution"}, {"screen_name": "PokemonGoPH", "full_name": "Pokemon Go PH"}, {"screen_name": "PoGO_PH", "full_name": "Pok\u00e9mon GO PH"}, {"screen_name": "officialLRT1", "full_name": "LRT1"}, {"screen_name": "NLJ_1", "full_name": "Nick Johnson"}, {"screen_name": "Freelancing_PH", "full_name": "Freelancing PH"}, {"screen_name": "askRCBC", "full_name": "RCBC"}, {"screen_name": "JeromeCMorales", "full_name": "JeromeCMorales"}, {"screen_name": "KeithpBarry", "full_name": "Keith Barry"}, {"screen_name": "the_contagious", "full_name": "Dave King"}, {"screen_name": "TayeDiggs", "full_name": "Taye Diggs"}, {"screen_name": "jacquemanabat", "full_name": "Jacque Manabat"}, {"screen_name": "glutenfreedoc", "full_name": "Dr. Doni Wilson"}, {"screen_name": "lenovo", "full_name": "Lenovo"}, {"screen_name": "carinecornelis", "full_name": "carine cornelis"}, {"screen_name": "Christine27King", "full_name": "Christine King"}, {"screen_name": "dotrmrt3", "full_name": "DOTr MRT-3"}, {"screen_name": "kristinesabillo", "full_name": "Kristine Sabillo"}, {"screen_name": "Official_UPD", "full_name": "UP Diliman"}, {"screen_name": "ruthilicious", "full_name": "Ruth dela Cruz"}, {"screen_name": "lourdesvindollo", "full_name": "nanayslunchesw/love"}, {"screen_name": "gingerarboleda", "full_name": "Ginger Arboleda"}, {"screen_name": "Blogapalooza", "full_name": "Blogapalooza Inc."}, {"screen_name": "Insarag", "full_name": "INSARAG"}, {"screen_name": "TupperwareWW", "full_name": "Tupperware Brands"}, {"screen_name": "penmanila", "full_name": "Butch Dalisay"}, {"screen_name": "jpsoriano", "full_name": "JP Soriano"}, {"screen_name": "GenKabiling", "full_name": "GenKabiling"}, {"screen_name": "bayangbarrios", "full_name": "bayang barrios"}, {"screen_name": "sj_nono", "full_name": "Nono Alfonso SJ"}, {"screen_name": "virtuallykaren", "full_name": "Karen (Melhuish) Spencer"}, {"screen_name": "ADB_HQ", "full_name": "AsianDevelopmentBank"}, {"screen_name": "OpenGov44", "full_name": "Open Gov (NARA)"}, {"screen_name": "opengovpart", "full_name": "Open Gov Partnership"}, {"screen_name": "township_mobile", "full_name": "Township"}, {"screen_name": "SalihSarikaya", "full_name": "Salih S."}, {"screen_name": "miguelrcamusINQ", "full_name": "Miguel R. Camus"}, {"screen_name": "pacae_seminars", "full_name": "PACAE"}, {"screen_name": "wilsonchua", "full_name": "wilson chua"}, {"screen_name": "shiereyes", "full_name": "Shiela Reyes"}, {"screen_name": "NicRobertsonCNN", "full_name": "Nic Robertson"}, {"screen_name": "BeckyCNN", "full_name": "Becky Anderson"}, {"screen_name": "rosemaryCNN", "full_name": "Rosemary Church"}, {"screen_name": "Bourdain", "full_name": "Anthony Bourdain"}, {"screen_name": "kristindeguzman", "full_name": "Kristine de Guzman-Yango"}, {"screen_name": "ClaireCeldran", "full_name": "Claire Celdran"}, {"screen_name": "MitziBorromeo", "full_name": "Mitzi Borromeo"}, {"screen_name": "peejayreyes", "full_name": "PJ Coronel Reyes"}, {"screen_name": "robertmanodzmm", "full_name": "robert mano"}, {"screen_name": "PiaBonalos", "full_name": "Pia Bonalos-Mercado"}, {"screen_name": "erwinaguilonINQ", "full_name": "Erwin Aguilon"}, {"screen_name": "AJEnglish", "full_name": "Al Jazeera English"}, {"screen_name": "WHOSEARO", "full_name": "WHO South-East Asia"}, {"screen_name": "Dok_Pau", "full_name": "Paulyn Rosell-Ubial"}, {"screen_name": "TridentDefense", "full_name": "Trident Defense"}, {"screen_name": "ProfRUM", "full_name": "Ronald U. Mendoza"}, {"screen_name": "reina_reyes", "full_name": "Reina Reyes"}, {"screen_name": "IvyPatdu", "full_name": "Ivy Patdu"}, {"screen_name": "ignaciomovie", "full_name": "IGNACIO (movie)"}, {"screen_name": "PokemonGoApp", "full_name": "Pok\u00e9mon GO"}, {"screen_name": "PokemonGoNews", "full_name": "Pok\u00e9mon GO News"}, {"screen_name": "PaoloDy", "full_name": "Paolo Dy"}, {"screen_name": "JesComPH", "full_name": "JesCom Philippines"}, {"screen_name": "Pokemon", "full_name": "Pok\u00e9mon"}, {"screen_name": "pagcorph", "full_name": "PAGCOR"}, {"screen_name": "KJPurisima", "full_name": "Toby Purisima"}, {"screen_name": "MTRCBgov", "full_name": "MTRCB"}, {"screen_name": "krizzy_kalerqui", "full_name": "\ud835\udc0c\ud835\udc22\ud835\udc2c\ud835\udc2c \ud835\udc0a\ud835\udc2b\ud835\udc22\ud835\udc33\ud835\udc33\ud835\udc32"}, {"screen_name": "All_Eskat", "full_name": "Scott"}, {"screen_name": "rubzonline", "full_name": "RUBY CABERTE"}, {"screen_name": "ABSCBNRedAlert", "full_name": "ABS-CBN Red Alert"}, {"screen_name": "brillante_ma", "full_name": "Brillante Mendoza"}, {"screen_name": "TheoandPhilo", "full_name": "Theo and Philo"}, {"screen_name": "OVPspox", "full_name": "Georgina Hernandez"}, {"screen_name": "JayDayupay", "full_name": "Jay Dayupay"}, {"screen_name": "Upwork", "full_name": "Upwork"}, {"screen_name": "sunstarcebu", "full_name": "SunStar Cebu"}, {"screen_name": "Stack_PH", "full_name": "Stack PH"}, {"screen_name": "adobomagazine", "full_name": "adobo magazine"}, {"screen_name": "markzambrano", "full_name": "Mark Zambrano"}, {"screen_name": "bawatbato", "full_name": "Bawat Bato"}, {"screen_name": "BrighterLifePH", "full_name": "Brighter Life PH"}, {"screen_name": "tinasrodriguez", "full_name": "Tina Santiago Rodriguez"}, {"screen_name": "RanhilioAquino", "full_name": "Fr. Ranhilio Aquino"}, {"screen_name": "stocksmartsph", "full_name": "StockSmarts"}, {"screen_name": "frsocvillegas", "full_name": "Socrates Villegas"}, {"screen_name": "RTVMalacanang", "full_name": "RTVMalacanang"}, {"screen_name": "ShorouqHamawi", "full_name": "Shorouq Hamawi"}, {"screen_name": "WranglerPH", "full_name": "Wrangler Philippines"}, {"screen_name": "Toblerone_PH", "full_name": "Toblerone PH"}, {"screen_name": "GrowthHackers", "full_name": "GrowthHackers"}, {"screen_name": "marlonmagtira", "full_name": "Marlon Magtira"}, {"screen_name": "KenLerona", "full_name": "Ken Lerona"}, {"screen_name": "PruLifeUK", "full_name": "Pru Life UK"}, {"screen_name": "podcastph", "full_name": "Podcast.Ph"}, {"screen_name": "sharemindfully", "full_name": "The Privacy Guru"}, {"screen_name": "BizBuzzAmerica", "full_name": "John Frazier"}, {"screen_name": "impulsecycle", "full_name": "Impulse Cycle"}, {"screen_name": "CynthiaLIVE", "full_name": "Cynthia Johnson"}, {"screen_name": "ml_chronicles", "full_name": "MLChronicles"}, {"screen_name": "NZinManila", "full_name": "NZ Embassy Manila"}, {"screen_name": "HeneralLuna", "full_name": "Heneral Antonio Luna"}, {"screen_name": "pericharcoalph", "full_name": "Peri-Peri Charcoal Chicken & Sauce Bar"}, {"screen_name": "janette_garin", "full_name": "Janette Garin"}, {"screen_name": "cleanseasph", "full_name": "Clean Seas Pilipinas"}, {"screen_name": "finkd", "full_name": "Mark Zuckerberg"}, {"screen_name": "MB_InaHernando", "full_name": "Ina Hernando-Malipot"}, {"screen_name": "gracecasin", "full_name": "Grace Casin \u00ae"}, {"screen_name": "victoriatulad", "full_name": "Victoria Tulad"}, {"screen_name": "tumblr", "full_name": "Tumblr"}, {"screen_name": "Pinterest", "full_name": "Pinterest"}, {"screen_name": "YouTube", "full_name": "YouTube"}, {"screen_name": "eyesgonzales", "full_name": "Iris Gonzales"}, {"screen_name": "brentcsutoras", "full_name": "Brent Csutoras"}, {"screen_name": "TigerMudra", "full_name": "\ud83d\udc2f TigerMudra \u00a0\ud83c\udf08"}, {"screen_name": "Malabon_City", "full_name": "MALABON CITY"}, {"screen_name": "bilbil", "full_name": "eloisa"}, {"screen_name": "paterno_II", "full_name": "Paterno Esmaquel II"}, {"screen_name": "Trefor1", "full_name": "Trefor Moss"}, {"screen_name": "KapuluanCoconut", "full_name": "Kapuluan Coconut"}, {"screen_name": "theWSIE", "full_name": "The World Summit"}, {"screen_name": "indaysara", "full_name": "Inday Sara Duterte"}, {"screen_name": "joescheesesteak", "full_name": "Joe's Cheesesteak"}, {"screen_name": "isabellamay", "full_name": "Isabella Montano"}, {"screen_name": "iflixph", "full_name": "iflix Philippines"}, {"screen_name": "DuterteRealTalk", "full_name": "Duterte Real Talk"}, {"screen_name": "jamsisante", "full_name": "Jam Sisante-Cayco"}, {"screen_name": "pompeelavina", "full_name": "POMPEE LA VI\u00d1A"}, {"screen_name": "perfectoyasay", "full_name": "Perfecto Yasay"}, {"screen_name": "mannypinol", "full_name": "emmanuel f. pinol"}, {"screen_name": "DMaliwanagINQ", "full_name": "Dennis Maliwanag"}, {"screen_name": "DeLimaJustice", "full_name": "Leila de Lima"}, {"screen_name": "PLDTEnterprise", "full_name": "PLDT Enterprise"}, {"screen_name": "btcph2016", "full_name": "BeTheChangePH"}, {"screen_name": "Wikipangako", "full_name": "Wikipangako"}, {"screen_name": "kateorson", "full_name": "Kate Orson"}, {"screen_name": "SecurityBankPH", "full_name": "Security Bank"}, {"screen_name": "GordonTredgold", "full_name": "Gordon Tredgold"}, {"screen_name": "CSRPhilippines", "full_name": "CSR Philippines"}, {"screen_name": "bicolstandard", "full_name": "Bicol Standard"}, {"screen_name": "NGCP_ALERT", "full_name": "NGCP"}, {"screen_name": "chasingrach", "full_name": "Rachel Hermosura \u00a0\ud83c\udf08"}, {"screen_name": "garrett_geoff", "full_name": "Geoffrey Garrett"}, {"screen_name": "NidoFortigrowPH", "full_name": "NIDO FORTIGROW"}, {"screen_name": "nimfaravelo", "full_name": "Nimfa R. Ravelo"}, {"screen_name": "PCWgovph", "full_name": "Commission on Women"}, {"screen_name": "peterlavina", "full_name": "Peter Lavina"}, {"screen_name": "ryandgreat", "full_name": "Ryan Greatuno \u00ae (\u91cc\u5b89)"}, {"screen_name": "mjaysoncayabyab", "full_name": "Marc Jayson Cayabyab"}, {"screen_name": "rodmagaru", "full_name": "Rod Magaru \u00a0\ud83c\uddf5\ud83c\udded"}, {"screen_name": "UnCJSirena", "full_name": "unCJ Meilou Sirena"}, {"screen_name": "PangulongDigong", "full_name": "Rodrigo Roa Duterte"}, {"screen_name": "orla_barry", "full_name": "Orla Barry"}, {"screen_name": "24OrasGMA", "full_name": "24 Oras"}, {"screen_name": "YouScoop", "full_name": "YouScoop"}, {"screen_name": "endocrine_witch", "full_name": "Iris Thiele Isip Tan"}, {"screen_name": "VCM_PH", "full_name": "COMELEC VCM"}, {"screen_name": "BBCBreaking", "full_name": "BBC Breaking News"}, {"screen_name": "nytimesworld", "full_name": "New York Times World"}, {"screen_name": "RussellShepherd", "full_name": "Russell Shepherd"}, {"screen_name": "piaranada", "full_name": "Pia Ranada"}, {"screen_name": "CaviteXpressway", "full_name": "CAVITEX (Official)"}, {"screen_name": "maynilad", "full_name": "Maynilad"}, {"screen_name": "OrbikPH", "full_name": "Orbik PH"}, {"screen_name": "AmazingiGrace", "full_name": "Amazing Grace"}, {"screen_name": "UNFPAph", "full_name": "UNFPA Philippines"}, {"screen_name": "livingMarjorney", "full_name": "Marjorie Uy / #WomanInDigital"}, {"screen_name": "BTwistsPH", "full_name": "Butterfly Twists Ph"}, {"screen_name": "ronallan", "full_name": "Ronald Allan"}, {"screen_name": "AlexVLapa", "full_name": "Alexandra Lapa"}, {"screen_name": "haveibeenpwned", "full_name": "Have I Been Pwned"}, {"screen_name": "PPCRV_National", "full_name": "PPCRV_National"}, {"screen_name": "troyhunt", "full_name": "Troy Hunt"}, {"screen_name": "ellainecdg", "full_name": "Ellaine Cruz"}, {"screen_name": "helloluis", "full_name": "luis buenaventura"}, {"screen_name": "netbloid", "full_name": "Netbloid"}, {"screen_name": "iamalexsantos", "full_name": "\uff21\uff2c\uff25\uff38 SANTOS"}, {"screen_name": "amps2482", "full_name": "angel"}, {"screen_name": "koriquintos", "full_name": "kori quintos"}, {"screen_name": "ArjayAbrea", "full_name": "Arjay Abrea"}, {"screen_name": "gdyagra", "full_name": "gwen.mom.md"}, {"screen_name": "GabrielaWomenPL", "full_name": "#37 Gabriela Women's Party"}, {"screen_name": "gretchenho", "full_name": "Gretchen Ho"}, {"screen_name": "sMark_ideas", "full_name": "Mark Raygan Garcia"}, {"screen_name": "upsystem", "full_name": "University of the Philippines"}, {"screen_name": "upncpagsc", "full_name": "UP NCPAG SC"}, {"screen_name": "bigballofstress", "full_name": "vlad"}, {"screen_name": "heyitspram", "full_name": "Pram Menghrajani"}, {"screen_name": "CHEDgovph", "full_name": "CHED.gov.ph"}, {"screen_name": "walangpasok", "full_name": "Walang Pasok!"}, {"screen_name": "pggsofficial", "full_name": "Philippine Good Governance Summit"}, {"screen_name": "mbtechlifestyle", "full_name": "MBTechLifestyle"}, {"screen_name": "ajbennettCNNPH", "full_name": "Armie Jarin-Bennett"}, {"screen_name": "LinksysPH", "full_name": "LinksysPH"}, {"screen_name": "BiteMe_Celina10", "full_name": "C"}, {"screen_name": "raffsantos", "full_name": "Raffy Sison Santos"}, {"screen_name": "pia_gutierrez", "full_name": "Pia Gutierrez"}, {"screen_name": "ragythomas", "full_name": "Ragy Thomas"}, {"screen_name": "livebettermedia", "full_name": "Live Better Media"}, {"screen_name": "iRegaloPH", "full_name": "iRegalo PH"}, {"screen_name": "calej", "full_name": "Calej"}, {"screen_name": "patsypat", "full_name": "patricia Paterno"}, {"screen_name": "rightrelevance", "full_name": "Right Relevance"}, {"screen_name": "CiletteLiboroCo", "full_name": "Cilette Liboro Co"}, {"screen_name": "10avendanoINQ", "full_name": "Ten Avendano"}, {"screen_name": "MediaNewserPhil", "full_name": "Media Newser Philippines"}, {"screen_name": "m1ready", "full_name": "Martin Aguda Jr."}, {"screen_name": "mara_elize", "full_name": "Mara Mercado"}, {"screen_name": "michellepestano", "full_name": "Michelle Fojas"}, {"screen_name": "Teddybird", "full_name": "Teddy Herbosa"}, {"screen_name": "stefdelacruzmd", "full_name": "Stef dela Cruz"}, {"screen_name": "DocWillieOng", "full_name": "Doc Willie Ong"}, {"screen_name": "janvicmateo", "full_name": "janvic"}, {"screen_name": "daxlucas", "full_name": "Dax"}, {"screen_name": "daxINQ", "full_name": "Daxim L. Lucas"}, {"screen_name": "SEVIrussnape", "full_name": "Miguel Sevidal"}, {"screen_name": "ePassPhils", "full_name": "ePassPhilippines"}, {"screen_name": "TheMuslimGayGuy", "full_name": "RHADEM"}, {"screen_name": "afdigitalsocial", "full_name": "AFDigital"}, {"screen_name": "business", "full_name": "Bloomberg"}, {"screen_name": "HHMommyOrdeals", "full_name": "Kait"}, {"screen_name": "KellerOfCapsule", "full_name": "Aaron Keller"}, {"screen_name": "AgeproofLiving", "full_name": "Ageproof Living"}, {"screen_name": "themarcoharder", "full_name": "Marco Harder"}, {"screen_name": "ReignGwapito", "full_name": "\u24e1\u24d4\u24d8\u24d6\u24dd\u2022\u24d6\u24e6\u24d0\u24df\u24d8\u24e3\u24de\u2122"}, {"screen_name": "NorWEIRDgian", "full_name": "Francine Prieto-Shotkoski"}, {"screen_name": "liadcruz", "full_name": "Lia Cruz"}, {"screen_name": "shawnyao", "full_name": "Shawn Yao"}, {"screen_name": "algore", "full_name": "Al Gore"}, {"screen_name": "NicoleCurato", "full_name": "Nicole Curato"}, {"screen_name": "bobreyes", "full_name": "Robert 'Bob' Reyes \u00a0\ud83c\uddf5\ud83c\udded"}, {"screen_name": "Bloomberg", "full_name": "Bloomberg LP"}, {"screen_name": "DigitalTrends", "full_name": "Digital Trends"}, {"screen_name": "AppleSupport", "full_name": "Apple Support"}, {"screen_name": "SpiralManila", "full_name": "Spiral Manila"}, {"screen_name": "SofitelManila", "full_name": "Sofitel Manila"}, {"screen_name": "Dusit_Manila", "full_name": "Dusit Thani Manila"}, {"screen_name": "MakatiShangriLa", "full_name": "Makati Shangri-La"}, {"screen_name": "EdsaShangriLa", "full_name": "Edsa Shangri-La"}, {"screen_name": "InstagramHeIp", "full_name": "Instagram Support"}, {"screen_name": "sofimi", "full_name": "\ud83c\udfbc GF\u266fE"}, {"screen_name": "reinatee", "full_name": "Maria Reina"}, {"screen_name": "JimLibiran", "full_name": "Jim Libiran"}, {"screen_name": "danabatnag", "full_name": "Dana Batnag"}, {"screen_name": "throwbackEDSA86", "full_name": "Throwback EDSA 1986"}, {"screen_name": "mikkievolante", "full_name": "Mikkie B Volante"}, {"screen_name": "vickygarch", "full_name": "Vicky Garchitorena"}, {"screen_name": "TheHackersNews", "full_name": "The Hacker News"}, {"screen_name": "PresidentePh", "full_name": "Presidentiables.Ph"}, {"screen_name": "ChairBautista", "full_name": "COMELEC Chairman"}, {"screen_name": "eflegara", "full_name": "Erika Legara"}, {"screen_name": "ChairAndyBau", "full_name": "Andy Bautista"}, {"screen_name": "stefsy", "full_name": "Stef Sy"}, {"screen_name": "SocialMoveTech", "full_name": "SMT"}, {"screen_name": "TwitterPH", "full_name": "Twitter Philippines"}, {"screen_name": "CasualConnect", "full_name": "Casual Connect"}, {"screen_name": "kontradaya", "full_name": "Kontra Daya"}, {"screen_name": "GovtSmarsh", "full_name": "Smarsh for Gov"}, {"screen_name": "MichaelLevy", "full_name": "Michael Levy"}, {"screen_name": "MNTiquia", "full_name": "MalouTiquia"}, {"screen_name": "KayeDacer", "full_name": "\u2728Kaye O. Dacer\u00a0\u2728"}, {"screen_name": "EtihadAirways", "full_name": "Etihad Airways"}, {"screen_name": "yogajane", "full_name": "Jane Uymatiao"}, {"screen_name": "jack", "full_name": "jack"}, {"screen_name": "BilangPilipino", "full_name": "Bilang Pilipino"}, {"screen_name": "meedan", "full_name": "meedan"}, {"screen_name": "speakbridge", "full_name": "Bridge (beta)"}, {"screen_name": "AteneoVox", "full_name": "AVox"}, {"screen_name": "EasondeGuzman", "full_name": "Eason de Guzman Jr"}, {"screen_name": "axncashcabph", "full_name": "Cash Cab PH"}, {"screen_name": "jullianeloved", "full_name": "Julliane de Jesus"}, {"screen_name": "FMangosingINQ", "full_name": "Frances Mangosing"}, {"screen_name": "chriseedelapaz", "full_name": "Chrisee V. Dela Paz"}, {"screen_name": "FloydWhaley", "full_name": "Floyd Whaley"}, {"screen_name": "DropboxSupport", "full_name": "Dropbox Support"}, {"screen_name": "GMA_PA", "full_name": "GMA Public Affairs"}, {"screen_name": "RRD_Davao", "full_name": "Rodrigo R. Duterte"}, {"screen_name": "peopleschoicegk", "full_name": "People's Choice"}, {"screen_name": "Flipboard", "full_name": "Flipboard"}, {"screen_name": "MrQuickiePH", "full_name": "Mr. Quickie"}, {"screen_name": "TeamKikoPH", "full_name": "Team Kiko"}, {"screen_name": "piofronda94", "full_name": "Pio Fronda"}, {"screen_name": "LabanLeni", "full_name": "LabanLeni"}, {"screen_name": "InquirerMobile", "full_name": "Inquirer Mobile"}, {"screen_name": "commrguanzon", "full_name": "Rowena V. Guanzon"}, {"screen_name": "jm_mayhem", "full_name": "JMTuazoned"}, {"screen_name": "Spotify_PH", "full_name": "Spotify Philippines"}, {"screen_name": "ASUSph", "full_name": "ASUS Philippines"}, {"screen_name": "JamesMSama", "full_name": "James Michael Sama"}, {"screen_name": "pia_mimaropa", "full_name": "PIA MIMAROPA"}, {"screen_name": "jsm2272", "full_name": "Julie Millan"}, {"screen_name": "JomsOfGlobe", "full_name": "Joms of Globe"}, {"screen_name": "philbertdy", "full_name": "Phil Dy"}, {"screen_name": "thebeatles", "full_name": "The Beatles"}, {"screen_name": "RizalGov", "full_name": "Rizal Provincial Gov"}, {"screen_name": "LapisPH", "full_name": "LAPIS Philippines"}, {"screen_name": "HGorganic", "full_name": "Homegrown Organics"}, {"screen_name": "FireQuinito", "full_name": "Jaemark Tordecilla"}, {"screen_name": "riasangabriel", "full_name": "Ria San Gabriel"}, {"screen_name": "ALERTolentino", "full_name": "Francis Tolentino"}, {"screen_name": "Forbes_PH", "full_name": "Forbes Philippines"}, {"screen_name": "DisneyPH", "full_name": "Disney PH"}, {"screen_name": "sheena_orlson", "full_name": "Sheena Opulencia"}, {"screen_name": "worldbankdata", "full_name": "World Bank Data"}, {"screen_name": "EdsonCGuido", "full_name": "Edson"}, {"screen_name": "thinkdatasci", "full_name": "Thinking Machines"}, {"screen_name": "BarackObante", "full_name": "Kenneth Abante"}, {"screen_name": "DavidInglesTV", "full_name": "David Ingles"}, {"screen_name": "Menardconnect", "full_name": "Menard Osena"}, {"screen_name": "apec2015ph", "full_name": "APEC 2015"}, {"screen_name": "APEC_CEOsummit", "full_name": "Asia Pacific Business News"}, {"screen_name": "Bollard_APEC", "full_name": "Alan Bollard"}, {"screen_name": "FreeKindleBook4", "full_name": "Free Kindle Books"}, {"screen_name": "BookBub", "full_name": "BookBub"}, {"screen_name": "edXOnline", "full_name": "edX"}, {"screen_name": "Zenutrients", "full_name": "Zenutrients"}, {"screen_name": "youthleadphil", "full_name": "I TRANSFORM! YOUNG LEADERS CONVENTION"}, {"screen_name": "attyjong", "full_name": "Jong Snow"}, {"screen_name": "attyvera", "full_name": "Dean Rod P. Vera"}, {"screen_name": "rejjventress", "full_name": "Regina Layug-Rosero"}, {"screen_name": "pinoy501st", "full_name": "Philippine Garrison"}, {"screen_name": "TristanNodalo", "full_name": "Tristan"}, {"screen_name": "OTS_DOTr", "full_name": "OTS"}, {"screen_name": "alden_lourinne", "full_name": "Alden Lourinne"}, {"screen_name": "aldubforlumad", "full_name": "aldubforlumad"}, {"screen_name": "AsiaBloom", "full_name": "Greg Bloom"}, {"screen_name": "tsinelasleader", "full_name": "TsinelasLeader"}, {"screen_name": "schadow1", "full_name": "Ervin Malicdem"}, {"screen_name": "emmainmanila", "full_name": "Emma Nagy"}, {"screen_name": "ovlizardo", "full_name": "Oscar Lizardo"}, {"screen_name": "WVAsia", "full_name": "WV Asia-Pacific"}, {"screen_name": "JustinTrudeau", "full_name": "Justin Trudeau"}, {"screen_name": "JDPasricha", "full_name": "Coaching Gender/Sex"}, {"screen_name": "FreelanceBlend", "full_name": "Marv de Leon"}, {"screen_name": "ExtremeStorms", "full_name": "Jim Edds"}, {"screen_name": "YGonzalesINQ", "full_name": "Yuji Gonzales"}, {"screen_name": "dswdspeaks", "full_name": "DSWD Spokesperson"}, {"screen_name": "mstoyang", "full_name": "ms toyang"}, {"screen_name": "mannypacquiao", "full_name": "Manny Pacquiao"}, {"screen_name": "olivarezeric", "full_name": "Eric L. Olivarez"}, {"screen_name": "SergeOsmena", "full_name": "Serge Osme\u00f1a"}, {"screen_name": "MarikinaLGU", "full_name": "Marikina Cenacle"}, {"screen_name": "SenLeiladeLima", "full_name": "Leila de Lima"}, {"screen_name": "usapinglacson", "full_name": "UsaPingLacson"}, {"screen_name": "tatakbotante", "full_name": "Tatak Botante"}, {"screen_name": "Asia_Foundation", "full_name": "The Asia Foundation"}, {"screen_name": "TheEconomist", "full_name": "The Economist"}, {"screen_name": "SocialWeatherPH", "full_name": "SWS"}, {"screen_name": "wef", "full_name": "World Economic Forum"}, {"screen_name": "aquino_edna", "full_name": "edna aquino"}, {"screen_name": "ronzheimer", "full_name": "Paul Ronzheimer"}, {"screen_name": "richardquest", "full_name": "Richard Quest"}, {"screen_name": "AndreeArchbold", "full_name": "Andr\u00e9e Archbold"}, {"screen_name": "iammarlonramos", "full_name": "Marlon Ramos"}, {"screen_name": "BamAlegre_", "full_name": "Bam Alegre"}, {"screen_name": "fotiniali", "full_name": "fotini ali"}, {"screen_name": "KristinKneedler", "full_name": "Kristin Kneedler"}, {"screen_name": "YujaWang", "full_name": "Yuja"}, {"screen_name": "FreedomofPress", "full_name": "Freedom of the Press"}, {"screen_name": "Snowden", "full_name": "Edward Snowden"}, {"screen_name": "By_the_roadside", "full_name": "Eduardo Dayrit"}, {"screen_name": "burgmarce", "full_name": "Maricel Burgonio"}, {"screen_name": "SolGenPH", "full_name": "SolGenPH"}, {"screen_name": "GoogleCR", "full_name": "GoogleCrisisResponse"}, {"screen_name": "BillGates", "full_name": "Bill Gates"}, {"screen_name": "acarvin", "full_name": "Andy Carvin"}, {"screen_name": "WFP", "full_name": "World Food Programme"}, {"screen_name": "Gabay_Kristo", "full_name": "Gabay Kristo"}, {"screen_name": "ChairmanFNT", "full_name": "Francis Tolentino"}, {"screen_name": "drgabbypelicci", "full_name": "GabriellePelicci PhD"}, {"screen_name": "AFPManila", "full_name": "AFPManila"}, {"screen_name": "zhandercayabyab", "full_name": "Zhander Cayabyab"}, {"screen_name": "wmginez", "full_name": "Winston M. Ginez"}, {"screen_name": "maderazo_jake", "full_name": "jakejmaderazo"}, {"screen_name": "DavidOroDZMM", "full_name": "DAVID HALLIG ORO"}, {"screen_name": "NoelAlamarDZMM", "full_name": "Noel S. Alamar"}, {"screen_name": "Dennis_Datu", "full_name": "Dennis  Cabral Datu"}, {"screen_name": "amfezam", "full_name": "Fe B. Zamora"}, {"screen_name": "rongagalac", "full_name": "Ron Gagalac"}, {"screen_name": "Uber", "full_name": "Uber"}, {"screen_name": "RoicesNaguit", "full_name": "Roices Naguit"}, {"screen_name": "KarenKeller", "full_name": "Karen Keller"}, {"screen_name": "ps3_ireport", "full_name": "Mandaluyong Police"}, {"screen_name": "PasaySPDReact", "full_name": "PasaySPDReact"}, {"screen_name": "MuntinlupaPulis", "full_name": "Muntinlupa Police"}, {"screen_name": "PNPHPG", "full_name": "HIGHWAY PATROL GROUP"}, {"screen_name": "Cathy__Yang", "full_name": "Cathy Yang"}, {"screen_name": "AFLagdameo", "full_name": "Antonio F. Lagdameo"}, {"screen_name": "repnancycatamco", "full_name": "Nancy Catamco"}, {"screen_name": "beacon_by", "full_name": "Beacon"}, {"screen_name": "DrFeliceGersh", "full_name": "Felice Gersh MD"}, {"screen_name": "tinapperez", "full_name": "Tina PanganibanPerez"}, {"screen_name": "jv_arcena", "full_name": "JV Lim Arcena"}, {"screen_name": "EDSA_PH", "full_name": "EDSA"}, {"screen_name": "AFP", "full_name": "AFP news agency"}, {"screen_name": "edsatraffic", "full_name": "EDSA Traffic"}, {"screen_name": "chowking_ph", "full_name": "Chowking"}, {"screen_name": "GoldilocksPH", "full_name": "Goldilocks PH"}, {"screen_name": "AyalaMalls", "full_name": "Ayala Malls"}, {"screen_name": "greenwichpizza", "full_name": "Greenwich Pizza"}, {"screen_name": "pizzahutphils", "full_name": "Pizza Hut Phils"}, {"screen_name": "USAID_Manila", "full_name": "USAID Philippines"}, {"screen_name": "vRush_ph", "full_name": "vRush_PH"}, {"screen_name": "serbisyoaccess", "full_name": "Serbisyo All Access"}, {"screen_name": "JohnsonManabat", "full_name": "Johnson L. Manabat"}, {"screen_name": "SCPIOChief", "full_name": "SCPIOChief"}, {"screen_name": "gavinbarfield", "full_name": "Gavin Barfield"}, {"screen_name": "marlo_knapp", "full_name": "Marlo Knapp"}, {"screen_name": "gadgetmatch", "full_name": "GadgetMatch"}, {"screen_name": "amiciphilippine", "full_name": "amiciphilippines"}, {"screen_name": "melenadem", "full_name": "m.elena de matteo"}, {"screen_name": "ePayPilipinas", "full_name": "ePay Pilipinas"}, {"screen_name": "MargaretSimons", "full_name": "MargaretSimons"}, {"screen_name": "Citi", "full_name": "Citi"}, {"screen_name": "journalism_melb", "full_name": "Unimelb Journalism"}, {"screen_name": "Kailash_a", "full_name": "Kailash"}, {"screen_name": "danertzzz", "full_name": "Dana M. Alberto"}, {"screen_name": "jepoyeng", "full_name": "Jepoy Bengero"}, {"screen_name": "drbobwright", "full_name": "Dr. Bob Wright"}, {"screen_name": "mang_tani", "full_name": "Nathaniel Cruz"}, {"screen_name": "franchesca_chai", "full_name": "\u2605 Chai \u2605"}, {"screen_name": "MommyWorkoutsUS", "full_name": "Mommy Workouts"}, {"screen_name": "participatory", "full_name": "Tiago C. Peixoto"}, {"screen_name": "StanfordGSB", "full_name": "Stanford Business"}, {"screen_name": "Inc", "full_name": "Inc."}, {"screen_name": "WSJ", "full_name": "The Wall Street Journal"}, {"screen_name": "HarvardBiz", "full_name": "Harvard Biz Review"}, {"screen_name": "JeffThindwa", "full_name": "Jeff Thindwa"}, {"screen_name": "jeffcrisostomo", "full_name": "Jeff Crisostomo #88AKBAYAN"}, {"screen_name": "AEsguerraINQ", "full_name": "Anthony Q. Esguerra"}, {"screen_name": "JonathanTorke", "full_name": "Jonathan Torke"}, {"screen_name": "Ppostofficial", "full_name": "PHLPost OFFICIAL"}, {"screen_name": "BangkoSentral", "full_name": "Bangko Sentral"}, {"screen_name": "MPD_react", "full_name": "Manila Police"}, {"screen_name": "misterjpmanahan", "full_name": "John Paul Manahan"}, {"screen_name": "TheBookTweeters", "full_name": "Book Tweeters"}, {"screen_name": "pinoyjesuits", "full_name": "Pinoy Jesuits"}, {"screen_name": "backupery", "full_name": "Backupery"}, {"screen_name": "binalot", "full_name": "Binalot Fiesta Foods"}, {"screen_name": "simplymeasured", "full_name": "Simply Measured"}, {"screen_name": "RomanRomulo", "full_name": "Roman Romulo"}, {"screen_name": "nujp", "full_name": "NUJP"}, {"screen_name": "OnePalafoxTeam", "full_name": "Palafox Associates"}, {"screen_name": "WellnessTipero", "full_name": "Wellness Tips"}, {"screen_name": "risingvoices", "full_name": "risingvoices"}, {"screen_name": "istarbucksmenu", "full_name": "Secret Starbucks"}, {"screen_name": "stratandbiz", "full_name": "strategy+business"}, {"screen_name": "BCG", "full_name": "Boston Consulting Group"}, {"screen_name": "McKinsey", "full_name": "McKinsey & Company"}, {"screen_name": "KPMG", "full_name": "KPMG"}, {"screen_name": "Navotas_City", "full_name": "Navotas City"}, {"screen_name": "Marikina1800", "full_name": "Marikina News"}, {"screen_name": "IloveTaguig1", "full_name": "I Love Taguig"}, {"screen_name": "PasayPIO", "full_name": "PasayPIO"}, {"screen_name": "MandaluyongDRRM", "full_name": "Mandaluyong CDRRMO"}, {"screen_name": "PIOCaloocan", "full_name": "CALOOCAN Public Info"}, {"screen_name": "OFFICIALMUNTI", "full_name": "OFFICIAL MUNTINLUPA"}, {"screen_name": "UNOCHA_Pacific", "full_name": "UN OCHA Pacific"}, {"screen_name": "HumanityRoad", "full_name": "Humanity Road"}, {"screen_name": "cfedmha", "full_name": "CFE-DM"}, {"screen_name": "mikebueza", "full_name": "Michael Bueza"}, {"screen_name": "carolyn_bonquin", "full_name": "Carolyn Bonquin"}, {"screen_name": "UNDPPH", "full_name": "UNDP Philippines"}, {"screen_name": "jhenallegadoINQ", "full_name": "Jennifer S. Allegado"}, {"screen_name": "alexisbromero", "full_name": "Alexis B. Romero"}, {"screen_name": "ReggieLay", "full_name": "Regina Lay"}, {"screen_name": "mtrpires", "full_name": "Marco T\u00falio Pires"}, {"screen_name": "CelinaAgaton", "full_name": "CelinaAgaton"}, {"screen_name": "hannahdormido", "full_name": "Hannah Dormido"}, {"screen_name": "ivyong_ph", "full_name": "Ivy Ong"}, {"screen_name": "noeL_maS", "full_name": "Sam Leon"}, {"screen_name": "SchoolOfData", "full_name": "School of Data"}, {"screen_name": "OKFN", "full_name": "Open Knowledge Intl"}, {"screen_name": "Nico_CAN_DO", "full_name": "Mailman"}, {"screen_name": "SMHome_Ph", "full_name": "SM Home"}, {"screen_name": "HPGPNP", "full_name": "Highway Patrol Group"}, {"screen_name": "internetsociety", "full_name": "Internet Society"}, {"screen_name": "klustout", "full_name": "Kristie Lu Stout\u00a0\u270c\ud83c\udffd"}, {"screen_name": "UPManilaOnline", "full_name": "UP MANILA (Official)"}, {"screen_name": "sahan_c", "full_name": "SahanCooray"}, {"screen_name": "coolbeans_ph", "full_name": "CoolBeansLibraryCafe"}, {"screen_name": "KrispyKremePH", "full_name": "Krispy Kreme PH"}, {"screen_name": "AirAsiaFilipino", "full_name": "AirAsiaFilipino"}, {"screen_name": "AllertaPH", "full_name": "Allerta"}, {"screen_name": "nbsalert", "full_name": "National Book Store"}, {"screen_name": "PLDT_Cares", "full_name": "PLDT Cares"}, {"screen_name": "OCASupremeCourt", "full_name": "The OCA"}, {"screen_name": "SCJudDev", "full_name": "SC Judicial Dev't"}, {"screen_name": "whycani", "full_name": "w milton"}, {"screen_name": "raisaserafica", "full_name": "Raisa Serafica"}, {"screen_name": "kafelokalph", "full_name": "kafelokal"}, {"screen_name": "alexlacson12", "full_name": "Alex Lacson"}, {"screen_name": "Politiko_Ph", "full_name": "Politiko"}, {"screen_name": "incitegov", "full_name": "INCITEGov"}, {"screen_name": "GoldsGymPH", "full_name": "GoldsGymPhilippines"}, {"screen_name": "GREATwomenASEAN", "full_name": "GREAT WOMEN"}, {"screen_name": "lynvgarcia", "full_name": "Coach Lyn Garcia"}, {"screen_name": "creativoices", "full_name": "CREATIVOICES"}, {"screen_name": "Joeltaborasj", "full_name": "Joel Tabora, SJ"}, {"screen_name": "Team_GracePoe", "full_name": "#TeamGracePoe"}, {"screen_name": "BW", "full_name": "Businessweek"}, {"screen_name": "FT", "full_name": "Financial Times"}, {"screen_name": "selectaicecream", "full_name": "Selecta Philippines"}, {"screen_name": "costacoffeeph", "full_name": "Costa Coffee Philippines"}, {"screen_name": "pinoyurbanist", "full_name": "Paulo Alcazaren"}, {"screen_name": "dsoshalnetwork", "full_name": "T.S.N."}, {"screen_name": "ASEANUP", "full_name": "ASEAN UP"}, {"screen_name": "TheFQMom", "full_name": "Rose Fres Fausto"}, {"screen_name": "BuddhaBarMNL", "full_name": "Buddha-Bar Manila"}, {"screen_name": "USTCComelec", "full_name": "UST Central COMELEC"}, {"screen_name": "ReproRights", "full_name": "Center for Reproductive Rights"}, {"screen_name": "yvette_tan", "full_name": "Avant Gardener"}, {"screen_name": "JILLRESONTOC", "full_name": "JILL RESONTOC - DWIZ -882 AM radio"}, {"screen_name": "voicecarepinas", "full_name": "Voice Care Pilipinas"}, {"screen_name": "AKTIBOTO", "full_name": "AKTIBOTO"}, {"screen_name": "object404", "full_name": "Carlos Nazareno"}, {"screen_name": "ichuvillanueva", "full_name": "Marichu Villanueva"}, {"screen_name": "PinterestPH", "full_name": "Pinterest PH"}, {"screen_name": "pcced", "full_name": "PH Civic Education"}, {"screen_name": "sarchavez", "full_name": "Cesar Chavez"}, {"screen_name": "ace_magdalo", "full_name": "Ashley Acedillo"}, {"screen_name": "yvoteph", "full_name": "YouthVotePhilippines"}, {"screen_name": "ChrisNicholsNFI", "full_name": "Chris Nichols"}, {"screen_name": "TopGearPh", "full_name": "Top Gear Philippines"}, {"screen_name": "maxlimpag", "full_name": "Max Limpag"}, {"screen_name": "MonetteHamlin", "full_name": "Monette Hamlin"}, {"screen_name": "RexRemitio", "full_name": "Rex Remitio"}, {"screen_name": "invoker", "full_name": "Ryan Holmes"}, {"screen_name": "iampinglacson", "full_name": "PING LACSON"}, {"screen_name": "officialSOCC", "full_name": "UST SOCC"}, {"screen_name": "youthpowerradio", "full_name": "Youth Power Radio"}, {"screen_name": "raymondnaguit", "full_name": "RJ Naguit #88Akbayan"}, {"screen_name": "UpliftingCont", "full_name": "Uplifting Content"}, {"screen_name": "BBCWorld", "full_name": "BBC News (World)"}, {"screen_name": "Newsweek", "full_name": "Newsweek"}, {"screen_name": "PNBph", "full_name": "PNB"}, {"screen_name": "Caitlyn_Jenner", "full_name": "Caitlyn Jenner"}, {"screen_name": "AngAlvin", "full_name": "Alvin P. Ang"}, {"screen_name": "meldyfider", "full_name": "meldy fider"}, {"screen_name": "clasajr", "full_name": "Carlos I Lasa Jr"}, {"screen_name": "efren7962", "full_name": "Efren Ll. Cruz, RFP"}, {"screen_name": "jessuysg", "full_name": "Jess Uy"}, {"screen_name": "lifehackorg", "full_name": "Lifehack"}, {"screen_name": "booksforlessph", "full_name": "Books for Less PH"}, {"screen_name": "NovuhairNatural", "full_name": "Novuhair"}, {"screen_name": "cheryltiu", "full_name": "Cheryl Tiu"}, {"screen_name": "barcy41479", "full_name": "Tony Stank"}, {"screen_name": "LTOCentral", "full_name": "LTO Central"}, {"screen_name": "LouGepuela", "full_name": "lougepuela"}, {"screen_name": "MoneyMaxPH", "full_name": "MoneyMax.ph"}, {"screen_name": "SaveChildrenPH", "full_name": "Save the Children PH"}, {"screen_name": "Howdy_Jed", "full_name": "Jed Adao"}, {"screen_name": "techinasia", "full_name": "Tech in Asia"}, {"screen_name": "HillaryClinton", "full_name": "Hillary Clinton"}, {"screen_name": "dalijet", "full_name": "Chris Daligault"}, {"screen_name": "BillClinton", "full_name": "Bill Clinton"}, {"screen_name": "POTUS44", "full_name": "President Obama"}, {"screen_name": "ANTHILL_Fabric", "full_name": "ANTHILLFabricGallery"}, {"screen_name": "eBooksLister", "full_name": "eBookLister"}, {"screen_name": "NealeGodfrey", "full_name": "Neale Godfrey"}, {"screen_name": "sapientialis", "full_name": "Lou"}, {"screen_name": "ben_carandang", "full_name": "Benedict Carandang"}, {"screen_name": "Char_Cruz", "full_name": "Char Cruz"}, {"screen_name": "TitasofManila", "full_name": "Titas of Manila"}, {"screen_name": "JackCanfield", "full_name": "Jack Canfield"}, {"screen_name": "TheZigZiglar", "full_name": "Zig Ziglar"}, {"screen_name": "TomZiglar", "full_name": "Tom Ziglar"}, {"screen_name": "EntreLeadership", "full_name": "EntreLeadership"}, {"screen_name": "gracet09", "full_name": "Grace Talusan"}, {"screen_name": "bayoclothing", "full_name": "BAYO"}, {"screen_name": "Twiplomacy", "full_name": "Twiplomacy \u00a0\ud83c\udf10"}, {"screen_name": "flightradar24", "full_name": "Flightradar24"}, {"screen_name": "dickc", "full_name": "dick costolo"}, {"screen_name": "LinkedInHelp", "full_name": "LinkedIn Help"}, {"screen_name": "PICTourism_ph", "full_name": "PICTourism"}, {"screen_name": "HunterCheryl", "full_name": "Cheryl Hunter"}, {"screen_name": "sherylsandberg", "full_name": "Sheryl Sandberg"}, {"screen_name": "OneLouderApps", "full_name": "OneLouder Apps"}, {"screen_name": "googlecalendar", "full_name": "Google Calendar"}, {"screen_name": "googledrive", "full_name": "Google Drive"}, {"screen_name": "inboxbygmail", "full_name": "Inbox by Gmail"}, {"screen_name": "YTCreators", "full_name": "YouTube Creators"}, {"screen_name": "GooglePlus", "full_name": "GooglePlus"}, {"screen_name": "elgammaofficial", "full_name": "El Gamma Penumbra"}, {"screen_name": "bethfrondoso", "full_name": "Lilibeth Frondoso"}, {"screen_name": "earlvalencia", "full_name": "Earl Martin Valencia"}, {"screen_name": "MishaFernandez", "full_name": "Mishael D. Fernandez"}, {"screen_name": "sanguit", "full_name": "Sangeet Paul C"}, {"screen_name": "ZachOnLinkedIn", "full_name": "Zachary Lukasiewicz"}, {"screen_name": "JULESguiang", "full_name": "jules guiang \u00a0\ud83c\uddf5\ud83c\udded"}, {"screen_name": "migrante_intl", "full_name": "Migrante Home Office"}, {"screen_name": "chefrobpengson", "full_name": "robpengson"}, {"screen_name": "reese_fernandez", "full_name": "Reese Fernandez-Ruiz"}, {"screen_name": "ViberHelp", "full_name": "ViberHelp"}, {"screen_name": "jeck_batallones", "full_name": "jeck batallones"}, {"screen_name": "UNHCRPh", "full_name": "UNHCR Philippines"}, {"screen_name": "BuzzFeedPH", "full_name": "BuzzFeed Philippines"}, {"screen_name": "WWIB", "full_name": "MBA Wharton Women"}, {"screen_name": "WhartonSchoolPR", "full_name": "Wharton PR & News"}, {"screen_name": "WhartonMBACM", "full_name": "Wharton MBA Careers"}, {"screen_name": "whartonknows", "full_name": "Knowledge@Wharton"}, {"screen_name": "jun_veneracion", "full_name": "Jun Veneracion"}, {"screen_name": "HavasOrtega", "full_name": "Havas Ortega"}, {"screen_name": "pragmactivist", "full_name": "Adam Greenberg \u00a0\ud83d\udd25"}, {"screen_name": "HuffPostTech", "full_name": "HuffPost Tech"}, {"screen_name": "TalinoEV", "full_name": "TalinoEV Systems"}, {"screen_name": "mangyanblogger", "full_name": "McRichard V. Paglicawan"}, {"screen_name": "leahbesajimenez", "full_name": "Leah Besa-Jimenez"}, {"screen_name": "EdSevidalDZMM", "full_name": "Edwin Sevidal"}, {"screen_name": "MicrosoftPH", "full_name": "MicrosoftPhilippines"}, {"screen_name": "pochology", "full_name": "POCHOLOGY"}, {"screen_name": "echomarket", "full_name": "ECHOmarket"}, {"screen_name": "rowiematti", "full_name": "Rowie Juan Matti"}, {"screen_name": "RommelJuan", "full_name": "Rommel Juan"}, {"screen_name": "Meikah", "full_name": "Meikah Yba\u00f1ez-Delid"}, {"screen_name": "mauieflores", "full_name": "Mauie Flores"}, {"screen_name": "DICTgovph", "full_name": "Department of ICT PH"}, {"screen_name": "birgovph", "full_name": "birgovph"}, {"screen_name": "polly_chic", "full_name": "Polly"}, {"screen_name": "wbg_gov", "full_name": "World Bank Gov"}, {"screen_name": "SeviSimavi", "full_name": "Sevi Simavi"}, {"screen_name": "mcoronelferrer", "full_name": "MiriamCoronelFerrer"}, {"screen_name": "stream", "full_name": "Stream"}, {"screen_name": "jmar777", "full_name": "Jeremy Martin"}, {"screen_name": "drbrendawade", "full_name": "Dr. Brenda Wade"}, {"screen_name": "worldbankfraud", "full_name": "WorldBankFraud"}, {"screen_name": "LinkedIn", "full_name": "LinkedIn"}, {"screen_name": "VMV", "full_name": "VMV HYPOALLERGENICS\u00ae"}, {"screen_name": "disasters_ph", "full_name": "disasters.ph"}, {"screen_name": "citizenengage", "full_name": "Citizen Engagement"}, {"screen_name": "joeyrossmaputi", "full_name": "Ross Maputi"}, {"screen_name": "michelle_d_ong", "full_name": "Michelle Krystle Ong"}, {"screen_name": "JavaheriCNN", "full_name": "Pedram Javaheri"}, {"screen_name": "teta_limcangco", "full_name": "Teta Limcangco"}, {"screen_name": "sinarproject", "full_name": "Sinar Project"}, {"screen_name": "tindakmalaysia", "full_name": "Tindak Malaysia"}, {"screen_name": "TIPhilippines", "full_name": "TI Philippines"}, {"screen_name": "dteare", "full_name": "Dave Teare"}, {"screen_name": "PeriscopeHelp", "full_name": "Periscope Help"}, {"screen_name": "giasison", "full_name": "Dr. Gia Sison"}, {"screen_name": "PeriscopeCo", "full_name": "Periscope"}, {"screen_name": "Stephane_Baudin", "full_name": "St\u00e9phane Baudin"}, {"screen_name": "dejiridoo", "full_name": "Deji Bryce Olukotun"}, {"screen_name": "leesebkk", "full_name": "Lisa Wills"}, {"screen_name": "levjoy", "full_name": "Josh Levy"}, {"screen_name": "eugeneyi", "full_name": "Eugene Yi"}, {"screen_name": "Onboardly", "full_name": "Onboardly"}, {"screen_name": "jasontcohen", "full_name": "Jason Cohen"}, {"screen_name": "AngelDAlucard", "full_name": "Dandelion"}, {"screen_name": "davidakaye", "full_name": "David Kaye"}, {"screen_name": "ffinggerfoods", "full_name": "ffingerfoods"}, {"screen_name": "OpenGarden", "full_name": "OpenGarden"}, {"screen_name": "ioerror", "full_name": "Jacob Appelbaum"}, {"screen_name": "dailypenn", "full_name": "The Daily Pennsylvanian"}, {"screen_name": "iamLOUBARRO", "full_name": "LOU BARRO"}, {"screen_name": "lkal213", "full_name": "Lisa Kalenkiewicz"}, {"screen_name": "nelsontenojo", "full_name": "TheLightedLamp"}, {"screen_name": "osbi", "full_name": "osbi"}, {"screen_name": "WorldMomsNetwk", "full_name": "World Moms Network"}, {"screen_name": "TempurInThePhil", "full_name": "TempurInthePhil"}, {"screen_name": "freenetph", "full_name": "freenet PH"}, {"screen_name": "OpenGovHub", "full_name": "Open Gov Hub"}, {"screen_name": "PNPDICTM", "full_name": "PNP DICTM"}, {"screen_name": "PSA_DataInfo", "full_name": "PSA Info"}, {"screen_name": "GENGregCatapang", "full_name": "Gregorio Catapang"}, {"screen_name": "CarlosTanGarces", "full_name": "Carlos Garces"}, {"screen_name": "We_Are_The_Web", "full_name": "WATW"}, {"screen_name": "SlideShare", "full_name": "LinkedIn SlideShare"}, {"screen_name": "Golcondia", "full_name": "GOLCONDIA Diamonds"}, {"screen_name": "EmmaWatson", "full_name": "Emma Watson"}, {"screen_name": "TheEllenShow", "full_name": "Ellen DeGeneres"}, {"screen_name": "SvensonPHL", "full_name": "Svenson"}, {"screen_name": "WomenSteppingUp", "full_name": "BPW Makati"}, {"screen_name": "memktgservices", "full_name": "Mandy Edwards"}, {"screen_name": "larrykim", "full_name": "Larry Kim"}, {"screen_name": "eLibraryUSA", "full_name": "eLibraryUSA"}, {"screen_name": "charleneli", "full_name": "Charlene Li"}, {"screen_name": "titopaeng", "full_name": "rafael alunan III"}, {"screen_name": "mama_lous", "full_name": "Mama Lou's Italian Kitchen"}, {"screen_name": "CitizensTraffic", "full_name": "Citizens' Traffic"}, {"screen_name": "childnet", "full_name": "Childnet"}, {"screen_name": "iKeepSafe", "full_name": "iKeepSafe"}, {"screen_name": "NetSafety101", "full_name": "Internet Safety 101"}, {"screen_name": "digitalparent", "full_name": "Digital Parent"}, {"screen_name": "parentsmagazine", "full_name": "Parents"}, {"screen_name": "GeorgeTakei", "full_name": "George Takei"}, {"screen_name": "AttyRAJI", "full_name": "Raji Mendoza"}, {"screen_name": "mlq3", "full_name": "Manuel L. Quezon III"}, {"screen_name": "marcbira", "full_name": "SI_FI FIRE  Sovereign Individual"}, {"screen_name": "TheRealNimoy", "full_name": "Leonard Nimoy"}, {"screen_name": "JustMrsASK", "full_name": "Anna Kohlmeier"}, {"screen_name": "paolapalma907", "full_name": "Paola Palma"}, {"screen_name": "M_i_c_h_a_e_l", "full_name": "M i c h a e l"}, {"screen_name": "drsanjaygupta", "full_name": "Dr. Sanjay Gupta"}, {"screen_name": "AmazonHelp", "full_name": "Amazon Help"}, {"screen_name": "ManageFlitter", "full_name": "ManageFlitter"}, {"screen_name": "EngagedSMM", "full_name": "Engaged Digital"}, {"screen_name": "racspalma", "full_name": "Sharlene Palma \u00a0\ud83c\udf4d"}, {"screen_name": "BreakingNews", "full_name": "Breaking News"}, {"screen_name": "uncletetsuPH", "full_name": "Uncle Tetsu PH"}, {"screen_name": "emmidejesus", "full_name": "Emmi de Jesus"}, {"screen_name": "nadiatrinidad", "full_name": "Nadia Trinidad"}, {"screen_name": "WhartonSocial", "full_name": "Wharton Social Impact"}, {"screen_name": "CenDemTech", "full_name": "Center for Democracy & Technology"}, {"screen_name": "guyberger", "full_name": "Guy Berger"}, {"screen_name": "netizenrights", "full_name": "Netizen Rights"}, {"screen_name": "solomonbrett", "full_name": "Brett Solomon"}, {"screen_name": "Internews", "full_name": "Internews"}, {"screen_name": "engageSPARK", "full_name": "engageSPARK"}, {"screen_name": "AdrianChen", "full_name": "Adrian Chen"}, {"screen_name": "WorldBank", "full_name": "World Bank"}, {"screen_name": "TaraJerika", "full_name": "Tara C \u00a0\ud83d\udc36\u00a0\ud83d\udc3e"}, {"screen_name": "ushahidi", "full_name": "Ushahidi"}, {"screen_name": "CoconutsManila", "full_name": "Coconuts Manila"}, {"screen_name": "boomanism", "full_name": "Boom Enriquez"}, {"screen_name": "paulscurtis", "full_name": "Paul Curtis"}, {"screen_name": "timesuptobacco", "full_name": "Time's Up, Tobacco!"}, {"screen_name": "ahrctweets", "full_name": "Ateneo Human Rights"}, {"screen_name": "pagibigfund", "full_name": "Pag-IBIG Fund"}, {"screen_name": "mia__reyes", "full_name": "mia__reyes"}, {"screen_name": "DMNTech", "full_name": "DMNTech"}, {"screen_name": "9tvph", "full_name": "9TV Philippines"}, {"screen_name": "cnnphilippines", "full_name": "CNN Philippines"}, {"screen_name": "LiveScience", "full_name": "Live Science"}, {"screen_name": "SwitchRightOn", "full_name": "Switch Right On"}, {"screen_name": "jeffjarvis", "full_name": "Jeff Jarvis"}, {"screen_name": "margaortigas", "full_name": "Marga Ortigas"}, {"screen_name": "KimIndar", "full_name": "kim indar"}, {"screen_name": "MandaluyongPIO", "full_name": "MandaluyongPIO"}, {"screen_name": "DILGkyusi", "full_name": "DILG Quezon City"}, {"screen_name": "safpio", "full_name": "saf pio"}, {"screen_name": "miroquimbo", "full_name": "Miro Quimbo"}, {"screen_name": "globalvoices", "full_name": "Global Voices"}, {"screen_name": "iACADEMY_EDU", "full_name": "iACADEMY"}, {"screen_name": "chryssac", "full_name": "Chryssa Celestino"}, {"screen_name": "catholiclink_en", "full_name": "CatholicLink English"}, {"screen_name": "Feli_Atienza", "full_name": "Felicia Hung Atienza"}, {"screen_name": "antoniospadaro", "full_name": "Antonio Spadaro"}, {"screen_name": "CatholicNewsSvc", "full_name": "Catholic News Service"}, {"screen_name": "Firechatapp", "full_name": "FireChat"}, {"screen_name": "papalvisitph", "full_name": "Papal Visit 2015"}, {"screen_name": "xendph", "full_name": "Xend"}, {"screen_name": "gwenpnava", "full_name": "gwenpnava"}, {"screen_name": "Official_DILG", "full_name": "DILG Official"}, {"screen_name": "LadyEaglesWay", "full_name": "Ateneo Lady Eagles \u00a0\ud83c\udfd0"}, {"screen_name": "alvinelchico", "full_name": "alvin elchico"}, {"screen_name": "Kremtopph", "full_name": "Krem-Top PH"}, {"screen_name": "isaavendanoDZIQ", "full_name": "Isa Avenda\u00f1o-Umali"}, {"screen_name": "SunLifePH", "full_name": "Sun Life PH"}, {"screen_name": "JamesMangun", "full_name": "James Mangun"}, {"screen_name": "MavyOfGlobe", "full_name": "MavyOfGlobe"}, {"screen_name": "ThermomixPhils", "full_name": "ThermomixPhils"}, {"screen_name": "inqmindanao", "full_name": "inqmindanao"}, {"screen_name": "tonyfernandes", "full_name": "Tony Fernandes"}, {"screen_name": "AirAsia", "full_name": "AirAsia"}, {"screen_name": "p2pdigital", "full_name": "Prep2Prime Digital"}, {"screen_name": "yugatech", "full_name": "YugaTech"}, {"screen_name": "westpacwx", "full_name": "Westpacwx"}, {"screen_name": "mic", "full_name": "Mic"}, {"screen_name": "amazon", "full_name": "Amazon.com"}, {"screen_name": "StevenRoodPH", "full_name": "Steven Rood"}, {"screen_name": "QuirkyBacon", "full_name": "The Quirky Bacon"}, {"screen_name": "ricruzricruz", "full_name": "Ricky Cruz"}, {"screen_name": "SedaHotels", "full_name": "Seda Hotels"}, {"screen_name": "TRESemmePH", "full_name": "TRESemm\u00e9 Philippines"}, {"screen_name": "GatoradePH", "full_name": "Gatorade Philippines"}, {"screen_name": "magnum_ph", "full_name": "Magnum Philippines"}, {"screen_name": "Rexona_PH", "full_name": "Rexona Philippines"}, {"screen_name": "UNIQLOPH", "full_name": "UNIQLO Philippines"}, {"screen_name": "benchtm", "full_name": "BENCH/"}, {"screen_name": "NescafePH", "full_name": "NESCAF\u00c9 Philippines"}, {"screen_name": "adidasph", "full_name": "adidas Philippines"}, {"screen_name": "CloseupPH", "full_name": "Closeup Philippines"}, {"screen_name": "WHOPhilippines", "full_name": "World Health Organization Philippines"}, {"screen_name": "LGPhilippines", "full_name": "LG Philippines"}, {"screen_name": "AcerPhils", "full_name": "Acer Philippines"}, {"screen_name": "SonyPHinc", "full_name": "Sony Philippines"}, {"screen_name": "AxePhilippines", "full_name": "Axe Philippines"}, {"screen_name": "OlayPhilippines", "full_name": "Olay Philippines"}, {"screen_name": "NIVEA_PH", "full_name": "NIVEA Philippines"}, {"screen_name": "TimexPH", "full_name": "Timex Philippines"}, {"screen_name": "EskinolPH", "full_name": "Eskinol Philippines"}, {"screen_name": "LazadaPH", "full_name": "Lazada Philippines"}, {"screen_name": "KedsPH", "full_name": "Keds Philippines"}, {"screen_name": "AvonPH", "full_name": "Avon Philippines"}, {"screen_name": "LevisPhil", "full_name": "Levi's Philippines"}, {"screen_name": "FordPhilippines", "full_name": "Ford Philippines"}, {"screen_name": "OreoPH", "full_name": "Oreo Philippines"}, {"screen_name": "KFCPhilippines", "full_name": "KFC Philippines"}, {"screen_name": "NCC_ph", "full_name": "NCC - Philippines"}, {"screen_name": "ZALORAPH", "full_name": "ZALORA Philippines"}, {"screen_name": "WWF_Philippines", "full_name": "WWF-Philippines"}, {"screen_name": "hmphilippines", "full_name": "H&M Philippines"}, {"screen_name": "mightyrasing", "full_name": "Mighty Rasing"}, {"screen_name": "agos", "full_name": "Agos"}, {"screen_name": "CSPhilippines", "full_name": "US Commercial Service Philippines"}, {"screen_name": "chowking", "full_name": "Chowking Pinoy"}, {"screen_name": "kitkat_ph", "full_name": "NESTL\u00c9 KIT KAT"}, {"screen_name": "governorespino", "full_name": "Amado T. Espino Jr."}, {"screen_name": "JVRufinoINQ", "full_name": "JV Rufino"}, {"screen_name": "TonyAbbottMHR", "full_name": "Tony Abbott"}, {"screen_name": "UN_Spokesperson", "full_name": "UN Spokesperson"}, {"screen_name": "officialdohgov", "full_name": "Department of Health"}, {"screen_name": "ASEAN", "full_name": "ASEAN"}, {"screen_name": "arpeelazaro", "full_name": "Arpee Lazaro"}, {"screen_name": "OCHAPhilippines", "full_name": "OCHA Philippines"}, {"screen_name": "OCHAAsiaPac", "full_name": "UN OCHA Asia Pacific"}, {"screen_name": "iabano", "full_name": "Imelda V. Abano"}, {"screen_name": "angelacasauay", "full_name": "Angela Casauay"}, {"screen_name": "joceldeguzman", "full_name": "Jocel de Guzman"}, {"screen_name": "perlherminado", "full_name": "perl herminado"}, {"screen_name": "rubyresponse", "full_name": "rubyresponsecluster"}, {"screen_name": "VanDamCNN", "full_name": "Derek Van Dam"}, {"screen_name": "PRO5React", "full_name": "KASUROG"}, {"screen_name": "DDRSNGO", "full_name": "DDRS"}, {"screen_name": "MikeAdcockWx", "full_name": "Mike Adcock"}, {"screen_name": "neilhimself", "full_name": "Neil Gaiman"}, {"screen_name": "CNNweather", "full_name": "CNN Weather Center"}, {"screen_name": "BrandonCNN", "full_name": "Brandon Miller"}, {"screen_name": "bubblyPH", "full_name": "Bubbly Philippines"}, {"screen_name": "cynoshaircareph", "full_name": "CynosInsideHairCare"}, {"screen_name": "nickinparadise", "full_name": "Nick Brown"}, {"screen_name": "WatsonsPH", "full_name": "Watsons Philippines"}, {"screen_name": "pbithos", "full_name": "Peter Bithos"}, {"screen_name": "GlobemyBusiness", "full_name": "Globe myBusiness"}, {"screen_name": "verified", "full_name": "Twitter Verified"}, {"screen_name": "nixnolledo", "full_name": "Nix Nolledo"}, {"screen_name": "GuyKawasaki", "full_name": "Guy Kawasaki"}, {"screen_name": "BrianPoeLl", "full_name": "Brian Poe Ll"}, {"screen_name": "WFP_Philippines", "full_name": "World Food Programme Philippines"}, {"screen_name": "niquashop", "full_name": "NiQua"}, {"screen_name": "digibizsummit", "full_name": "Digital Business"}, {"screen_name": "gmail", "full_name": "Gmail"}, {"screen_name": "TechCrunch", "full_name": "TechCrunch"}, {"screen_name": "clickclickclick", "full_name": "Click.Click.Click"}, {"screen_name": "fritzdrodriguez", "full_name": "fritzie rodriguez"}, {"screen_name": "justineletargo", "full_name": "Justine Letargo"}, {"screen_name": "WB_AsiaPacific", "full_name": "World Bank AsiaPac"}, {"screen_name": "TimKobe", "full_name": "Tim Kobe"}, {"screen_name": "TzuChiPH", "full_name": "Tzu Chi PH"}, {"screen_name": "govogingmercado", "full_name": "Roger G. Mercado"}, {"screen_name": "RedCrossYouthPH", "full_name": "Red Cross Youth"}, {"screen_name": "redcross143", "full_name": "Red Cross 143"}, {"screen_name": "88DBPhilippines", "full_name": "Service Portal"}, {"screen_name": "insularlife", "full_name": "Insular Life"}, {"screen_name": "makoipopioco", "full_name": "Makoi Popioco CNN PH"}, {"screen_name": "HSPnp", "full_name": "Pnp HS"}, {"screen_name": "rightscon", "full_name": "RightsCon"}, {"screen_name": "kay_bu", "full_name": "Kay Bunagan"}, {"screen_name": "PeopleSurge", "full_name": "People Surge"}, {"screen_name": "micheleborba", "full_name": "Dr. Michele Borba"}, {"screen_name": "socialgoodmoms", "full_name": "Social Good Moms"}, {"screen_name": "HPSupport", "full_name": "HP Support"}, {"screen_name": "dpcrpublicinfo", "full_name": "PNP DPCR PID"}, {"screen_name": "accessnow", "full_name": "Access Now"}, {"screen_name": "EngageMedia", "full_name": "EngageMedia"}, {"screen_name": "BantayBayanihan", "full_name": "Bantay Bayanihan"}, {"screen_name": "FMA_PH", "full_name": "FMA"}, {"screen_name": "PNPACG", "full_name": "PNP ACG"}, {"screen_name": "IIPCoordinator", "full_name": "IIP Coordinator"}, {"screen_name": "GeenaRocero", "full_name": "Geena Rocero"}, {"screen_name": "andrewcnn", "full_name": "Andrew Stevens"}, {"screen_name": "hilaryisaac", "full_name": "Hilary Isaac"}, {"screen_name": "RobSupermarket", "full_name": "RobinsonsSupermarket"}, {"screen_name": "PNP_PCRG", "full_name": "PCRG"}, {"screen_name": "drhenry4", "full_name": "DrHenry"}, {"screen_name": "nong2nong", "full_name": "Benny T"}, {"screen_name": "MarkSalazarGMA7", "full_name": "Mark Salazar"}, {"screen_name": "Aileesa", "full_name": "Aileesa Lim-Sua"}, {"screen_name": "aim_edu", "full_name": "Asian Institute of Management"}, {"screen_name": "AusAmbPH", "full_name": "Steve Robinson AO"}, {"screen_name": "balitangamerica", "full_name": "Balitang America"}, {"screen_name": "heyjoeshow", "full_name": "Hey Joe Show"}, {"screen_name": "rowenaparaan", "full_name": "Rowena Paraan"}, {"screen_name": "AteneoAssembly", "full_name": "The Ateneo Assembly"}]}